Workbook

Sheet CONSOLIDADO
A1: PRESUPUESTO 2025 — CUÑO CORRIENTE | MODELO RECONSTRUIDO
A2: Casa de Moneda de México | Correcciones acordadas: inflación 3.96%, TC 19.36, energía +15%, costos fijos +3.96%, sin doble suma de acuñación/cospeleo.
A4: SUPUESTOS DEL MODELO | E4: RESUMEN EJECUTIVO
A5: Factor de inflación 2025 | B5: 1.0396 | C5: 3.96% | E5: Presupuesto total corregido | F5: ='MESES 2025'!T17 -> 1.0173318e+10
A6: Tipo de cambio (MXN/USD) | B6: 19.36 | C6: Fijo en todo el documento | E6: Piezas anuales | F6: ='MESES 2025'!H17 -> 2.67e+09
A7: Incremento energía | B7: 0.15 | C7: Aplicado al costo unitario base 2024 | E7: Costo promedio por pieza | F7: =F5/F6 -> 3.8102315
A8: Costo unitario energía base 2024 | B8: 0.0071760695 | C8: MXN/pieza | E8: TC aplicado | F8: =B6 -> 19.36
A9: Costo unitario energía 2025 | B9: =B8*(1+B7) -> 0.0082524799 | C9: Base × (1 + 15%)
A10: Recuperación scrap | B10: 0.93 | C10: 93%
A11: Personal eventual mensual | B11: 37953243 | C11: MXN/mes
A12: Sobrecargos mensuales | B12: 22051466 | C12: MXN/mes
A13: Costo fijo acuñación base mensual | B13: 62754568 | C13: Valor contenido en archivo original
A14: Costo fijo cospel base mensual | B14: 3583069.5 | C14: Valor contenido en archivo original
A15: Factor actualización costos fijos | B15: 1.0396 | C15: Mismo factor de inflación: 3.96%
A18: DIAGRAMA DE INTEGRACIÓN DEL PRESUPUESTO
A20: DEMANDA BANXICO # piezas por denominación (hoja 3) | C20: → | D20: COSTOS VARIABLES Acuñación + Cospeleo + Acero + Bronce-Al + Alpaca | G20: → | H20: LIBRANZA ORDINARIA Incluye todos los costos variables
A25: PERSONAL EVENTUAL | C25: SOBRECARGOS | E25: ENERGÍA (+15%) | G25: COSTO FIJO ACUÑACIÓN (+3.96%) | I25: COSTO FIJO COSPEL (+3.96%)
A29: ↓ TODOS LOS CONCEPTOS ANTERIORES SE INTEGRAN UNA SOLA VEZ ↓
C32: TOTAL PRESUPUESTO 2025
A37: INTEGRACIÓN ANUAL DEL PRESUPUESTO
A38: Concepto | B38: Importe anual | C38: Tratamiento | D38: ¿Suma al total? | F38: Mes | G38: Presupuesto mensual | H38: Libranza | I38: Fijos | J38: Energía
A39: Acuñación variable | B39: ='MESES 2025'!I17 -> 57894006 | C39: Dentro de Libranza | D39: NO adicional | F39: Enero | G39: ='MESES 2025'!T5 -> 6.7115921e+08 | H39: ='MESES 2025'!N5 -> 5.4059557e+08 | I39: ='MESES 2025'!R5+'MESES 2025'!S5 -> 68964608 | J39: ='MESES 2025'!Q5 -> 1594325.6
A40: Cospeleo variable | B40: ='MESES 2025'!J17 -> 78948646 | C40: Dentro de Libranza | D40: NO adicional | F40: Febrero | G40: ='MESES 2025'!T6 -> 9.3323006e+08 | H40: ='MESES 2025'!N6 -> 8.0212859e+08 | I40: ='MESES 2025'!R6+'MESES 2025'!S6 -> 68964608 | J40: ='MESES 2025'!Q6 -> 2132150.3
A41: Acero inoxidable | B41: ='MESES 2025'!K17 -> 9.5412268e+08 | C41: Dentro de Libranza | D41: NO adicional | F41: Marzo | G41: ='MESES 2025'!T7 -> 9.3436807e+08 | H41: ='MESES 2025'!N7 -> 8.0361669e+08 | I41: ='MESES 2025'!R7+'MESES 2025'!S7 -> 68964608 | J41: ='MESES 2025'!Q7 -> 1782054.4
A42: Bronce-aluminio / NACOBRE | B42: ='MESES 2025'!L17 -> 7.0501596e+09 | C42: Dentro de Libranza | D42: NO adicional | F42: Abril | G42: ='MESES 2025'!T8 -> 5.7103502e+08 | H42: ='MESES 2025'!N8 -> 4.4069698e+08 | I42: ='MESES 2025'!R8+'MESES 2025'!S8 -> 68964608 | J42: ='MESES 2025'!Q8 -> 1368715.9
A43: Alpaca / CUNI | B43: ='MESES 2025'!M17 -> 4.6252715e+08 | C43: Dentro de Libranza | D43: NO adicional | F43: Mayo | G43: ='MESES 2025'!T9 -> 9.2768299e+08 | H43: ='MESES 2025'!N9 -> 7.962602e+08 | I43: ='MESES 2025'!R9+'MESES 2025'!S9 -> 68964608 | J43: ='MESES 2025'!Q9 -> 2453466.9
A44: Libranza ordinaria | B44: ='MESES 2025'!N17 -> 8.6036521e+09 | C44: Suma costos variables | D44: SÍ | F44: Junio | G44: ='MESES 2025'!T10 -> 1.0431017e+09 | H44: ='MESES 2025'!N10 -> 9.1244601e+08 | I44: ='MESES 2025'!R10+'MESES 2025'!S10 -> 68964608 | J44: ='MESES 2025'!Q10 -> 1686347.5
A45: Personal eventual | B45: ='MESES 2025'!O17 -> 4.5543891e+08 | C45: Costo adicional | D45: SÍ | F45: Julio | G45: ='MESES 2025'!T11 -> 5.9578188e+08 | H45: ='MESES 2025'!N11 -> 4.6591597e+08 | I45: ='MESES 2025'!R11+'MESES 2025'!S11 -> 68964608 | J45: ='MESES 2025'!Q11 -> 896589
A46: Sobrecargos | B46: ='MESES 2025'!P17 -> 2.6461759e+08 | C46: Costo adicional | D46: SÍ | F46: Agosto | G46: ='MESES 2025'!T12 -> 9.0709015e+08 | H46: ='MESES 2025'!N12 -> 7.7591288e+08 | I46: ='MESES 2025'!R12+'MESES 2025'!S12 -> 68964608 | J46: ='MESES 2025'!Q12 -> 2207946.1
A47: Energía eléctrica | B47: ='MESES 2025'!Q17 -> 22034121 | C47: Costo separado; +15% | D47: SÍ | F47: Septiembre | G47: ='MESES 2025'!T13 -> 1.0419973e+09 | H47: ='MESES 2025'!N13 -> 9.1062398e+08 | I47: ='MESES 2025'!R13+'MESES 2025'!S13 -> 68964608 | J47: ='MESES 2025'!Q13 -> 2403995.2
A48: Costo fijo acuñación | B48: ='MESES 2025'!R17 -> 7.8287579e+08 | C48: Actualizado 3.96% | D48: SÍ | F48: Octubre | G48: ='MESES 2025'!T14 -> 7.266475e+08 | H48: ='MESES 2025'!N14 -> 5.9569497e+08 | I48: ='MESES 2025'!R14+'MESES 2025'!S14 -> 68964608 | J48: ='MESES 2025'!Q14 -> 1983215.8
A49: Costo fijo cospel | B49: ='MESES 2025'!S17 -> 44699509 | C49: Actualizado 3.96% | D49: SÍ | F49: Noviembre | G49: ='MESES 2025'!T15 -> 1.0021088e+09 | H49: ='MESES 2025'!N15 -> 8.7097651e+08 | I49: ='MESES 2025'!R15+'MESES 2025'!S15 -> 68964608 | J49: ='MESES 2025'!Q15 -> 2162960.9
A50: TOTAL PRESUPUESTO | B50: ='MESES 2025'!T17 -> 1.0173318e+10 | C50: Sin dobles conteos | D50: SÍ | F50: Diciembre | G50: ='MESES 2025'!T16 -> 8.1911538e+08 | H50: ='MESES 2025'!N16 -> 6.8878371e+08 | I50: ='MESES 2025'!R16+'MESES 2025'!S16 -> 68964608 | J50: ='MESES 2025'!Q16 -> 1362353.6
A53: NOTAS DE TRAZABILIDAD Y REVISIÓN

Sheet MESES 2025
A1: CÁLCULO MENSUAL DEL PRESUPUESTO 2025
A4: Mes | B4: Pzas $0.50 | C4: Pzas $1 | D4: Pzas $2 | E4: Pzas $5 | F4: Pzas $10 | G4: Pzas $20 | H4: Total piezas | I4: Acuñación var. | J4: Cospeleo var. | K4: Acero inox. | L4: Bronce-Al | M4: Alpaca | N4: Libranza ordinaria | O4: Personal eventual | P4: Sobrecargos | Q4: Energía | R4: Fijo acuñación | S4: Fijo cospel | T4: TOTAL PRESUP.
A5: Enero | B5: ='DEMANDA BANXICO 2025'!B5*1000000 -> 83218841 | C5: ='DEMANDA BANXICO 2025'!C5*1000000 -> 35917078 | D5: ='DEMANDA BANXICO 2025'!D5*1000000 -> 16142802 | E5: ='DEMANDA BANXICO 2025'!E5*1000000 -> 35247076 | F5: ='DEMANDA BANXICO 2025'!F5*1000000 -> 19523042 | G5: ='DEMANDA BANXICO 2025'!G5*1000000 -> 3144678 | H5: =SUM(B5:G5) -> 1.9319352e+08 | I5: =B5*$B$25+C5*$C$25+D5*$D$25+E5*$E$25+F5*$F$25+G5*$G$25 -> 4255164.3 | J5: =B5*$B$28+C5*$C$28+D5*$D$28+E5*$E$28+F5*$F$28+G5*$G$28 -> 5273323.5 | K5: =SUMPRODUCT(B5:G5,'METALES 2025 BUENO'!B118:G118) -> 68023705 | L5: =SUMPRODUCT(B5:G5,'METALES 2025 BUENO'!B48:G48) -> 4.3178888e+08 | M5: =SUMPRODUCT(B5:G5,'METALES 2025 BUENO'!B90:G90) -> 31254489 | N5: =SUM(I5:M5) -> 5.4059557e+08 | O5: =CONSOLIDADO!$B$11 -> 37953243 | P5: =CONSOLIDADO!$B$12 -> 22051466 | Q5: =H5*CONSOLIDADO!$B$9 -> 1594325.6 | R5: =CONSOLIDADO!$B$13*CONSOLIDADO!$B$15 -> 65239649 | S5: =CONSOLIDADO!$B$14*CONSOLIDADO!$B$15 -> 3724959.1 | T5: =N5+O5+P5+Q5+R5+S5 -> 6.7115921e+08
A6: Febrero | B6: ='DEMANDA BANXICO 2025'!B6*1000000 -> 77781159 | C6: ='DEMANDA BANXICO 2025'!C6*1000000 -> 81504139 | D6: ='DEMANDA BANXICO 2025'!D6*1000000 -> 32135872 | E6: ='DEMANDA BANXICO 2025'!E6*1000000 -> 32669918 | F6: ='DEMANDA BANXICO 2025'!F6*1000000 -> 29540101 | G6: ='DEMANDA BANXICO 2025'!G6*1000000 -> 4733611.5 | H6: =SUM(B6:G6) -> 2.583648e+08 | I6: =B6*$B$25+C6*$C$25+D6*$D$25+E6*$E$25+F6*$F$25+G6*$G$25 -> 5743868.7 | J6: =B6*$B$28+C6*$C$28+D6*$D$28+E6*$E$28+F6*$F$28+G6*$G$28 -> 7561735.9 | K6: =SUMPRODUCT(B6:G6,'METALES 2025 BUENO'!B119:G119) -> 88350749 | L6: =SUMPRODUCT(B6:G6,'METALES 2025 BUENO'!B49:G49) -> 6.5317743e+08 | M6: =SUMPRODUCT(B6:G6,'METALES 2025 BUENO'!B91:G91) -> 47294810 | N6: =SUM(I6:M6) -> 8.0212859e+08 | O6: =CONSOLIDADO!$B$11 -> 37953243 | P6: =CONSOLIDADO!$B$12 -> 22051466 | Q6: =H6*CONSOLIDADO!$B$9 -> 2132150.3 | R6: =CONSOLIDADO!$B$13*CONSOLIDADO!$B$15 -> 65239649 | S6: =CONSOLIDADO!$B$14*CONSOLIDADO!$B$15 -> 3724959.1 | T6: =N6+O6+P6+Q6+R6+S6 -> 9.3323006e+08
A7: Marzo | B7: ='DEMANDA BANXICO 2025'!B7*1000000 -> 0 | C7: ='DEMANDA BANXICO 2025'!C7*1000000 -> 96328782 | D7: ='DEMANDA BANXICO 2025'!D7*1000000 -> 68721326 | E7: ='DEMANDA BANXICO 2025'!E7*1000000 -> 24333006 | F7: ='DEMANDA BANXICO 2025'!F7*1000000 -> 24436857 | G7: ='DEMANDA BANXICO 2025'!G7*1000000 -> 2121710.5 | H7: =SUM(B7:G7) -> 2.1594168e+08 | I7: =B7*$B$25+C7*$C$25+D7*$D$25+E7*$E$25+F7*$F$25+G7*$G$25 -> 4474468.6 | J7: =B7*$B$28+C7*$C$28+D7*$D$28+E7*$E$28+F7*$F$28+G7*$G$28 -> 6902102.3 | K7: =SUMPRODUCT(B7:G7,'METALES 2025 BUENO'!B120:G120) -> 82156217 | L7: =SUMPRODUCT(B7:G7,'METALES 2025 BUENO'!B50:G50) -> 6.7372249e+08 | M7: =SUMPRODUCT(B7:G7,'METALES 2025 BUENO'!B92:G92) -> 36361417 | N7: =SUM(I7:M7) -> 8.0361669e+08 | O7: =CONSOLIDADO!$B$11 -> 37953243 | P7: =CONSOLIDADO!$B$12 -> 22051466 | Q7: =H7*CONSOLIDADO!$B$9 -> 1782054.4 | R7: =CONSOLIDADO!$B$13*CONSOLIDADO!$B$15 -> 65239649 | S7: =CONSOLIDADO!$B$14*CONSOLIDADO!$B$15 -> 3724959.1 | T7: =N7+O7+P7+Q7+R7+S7 -> 9.3436807e+08
A8: Abril | B8: ='DEMANDA BANXICO 2025'!B8*1000000 -> 63699295 | C8: ='DEMANDA BANXICO 2025'!C8*1000000 -> 37436387 | D8: ='DEMANDA BANXICO 2025'!D8*1000000 -> 24554395 | E8: ='DEMANDA BANXICO 2025'!E8*1000000 -> 24956358 | F8: ='DEMANDA BANXICO 2025'!F8*1000000 -> 14129290 | G8: ='DEMANDA BANXICO 2025'!G8*1000000 -> 1079378.6 | H8: =SUM(B8:G8) -> 1.6585511e+08 | I8: =B8*$B$25+C8*$C$25+D8*$D$25+E8*$E$25+F8*$F$25+G8*$G$25 -> 3403528.3 | J8: =B8*$B$28+C8*$C$28+D8*$D$28+E8*$E$28+F8*$F$28+G8*$G$28 -> 4116527.9 | K8: =SUMPRODUCT(B8:G8,'METALES 2025 BUENO'!B121:G121) -> 60013583 | L8: =SUMPRODUCT(B8:G8,'METALES 2025 BUENO'!B51:G51) -> 3.523418e+08 | M8: =SUMPRODUCT(B8:G8,'METALES 2025 BUENO'!B93:G93) -> 20821545 | N8: =SUM(I8:M8) -> 4.4069698e+08 | O8: =CONSOLIDADO!$B$11 -> 37953243 | P8: =CONSOLIDADO!$B$12 -> 22051466 | Q8: =H8*CONSOLIDADO!$B$9 -> 1368715.9 | R8: =CONSOLIDADO!$B$13*CONSOLIDADO!$B$15 -> 65239649 | S8: =CONSOLIDADO!$B$14*CONSOLIDADO!$B$15 -> 3724959.1 | T8: =N8+O8+P8+Q8+R8+S8 -> 5.7103502e+08
A9: Mayo | B9: ='DEMANDA BANXICO 2025'!B9*1000000 -> 97270545 | C9: ='DEMANDA BANXICO 2025'!C9*1000000 -> 80807812 | D9: ='DEMANDA BANXICO 2025'!D9*1000000 -> 64673372 | E9: ='DEMANDA BANXICO 2025'!E9*1000000 -> 30108668 | F9: ='DEMANDA BANXICO 2025'!F9*1000000 -> 20662341 | G9: ='DEMANDA BANXICO 2025'!G9*1000000 -> 3777825.2 | H9: =SUM(B9:G9) -> 2.9730056e+08 | I9: =B9*$B$25+C9*$C$25+D9*$D$25+E9*$E$25+F9*$F$25+G9*$G$25 -> 6364707.9 | J9: =B9*$B$28+C9*$C$28+D9*$D$28+E9*$E$28+F9*$F$28+G9*$G$28 -> 7592251.8 | K9: =SUMPRODUCT(B9:G9,'METALES 2025 BUENO'!B122:G122) -> 1.0760491e+08 | L9: =SUMPRODUCT(B9:G9,'METALES 2025 BUENO'!B52:G52) -> 6.4074852e+08 | M9: =SUMPRODUCT(B9:G9,'METALES 2025 BUENO'!B94:G94) -> 33949809 | N9: =SUM(I9:M9) -> 7.962602e+08 | O9: =CONSOLIDADO!$B$11 -> 37953243 | P9: =CONSOLIDADO!$B$12 -> 22051466 | Q9: =H9*CONSOLIDADO!$B$9 -> 2453466.9 | R9: =CONSOLIDADO!$B$13*CONSOLIDADO!$B$15 -> 65239649 | S9: =CONSOLIDADO!$B$14*CONSOLIDADO!$B$15 -> 3724959.1 | T9: =N9+O9+P9+Q9+R9+S9 -> 9.2768299e+08
A10: Junio | B10: ='DEMANDA BANXICO 2025'!B10*1000000 -> 30159.608 | C10: ='DEMANDA BANXICO 2025'!C10*1000000 -> 95505801 | D10: ='DEMANDA BANXICO 2025'!D10*1000000 -> 27772233 | E10: ='DEMANDA BANXICO 2025'!E10*1000000 -> 37184974 | F10: ='DEMANDA BANXICO 2025'!F10*1000000 -> 38708369 | G10: ='DEMANDA BANXICO 2025'!G10*1000000 -> 5142796.1 | H10: =SUM(B10:G10) -> 2.0434433e+08 | I10: =B10*$B$25+C10*$C$25+D10*$D$25+E10*$E$25+F10*$F$25+G10*$G$25 -> 4705265.4 | J10: =B10*$B$28+C10*$C$28+D10*$D$28+E10*$E$28+F10*$F$28+G10*$G$28 -> 8028381.9 | K10: =SUMPRODUCT(B10:G10,'METALES 2025 BUENO'!B123:G123) -> 70912179 | L10: =SUMPRODUCT(B10:G10,'METALES 2025 BUENO'!B53:G53) -> 7.6815674e+08 | M10: =SUMPRODUCT(B10:G10,'METALES 2025 BUENO'!B95:G95) -> 60643450 | N10: =SUM(I10:M10) -> 9.1244601e+08 | O10: =CONSOLIDADO!$B$11 -> 37953243 | P10: =CONSOLIDADO!$B$12 -> 22051466 | Q10: =H10*CONSOLIDADO!$B$9 -> 1686347.5 | R10: =CONSOLIDADO!$B$13*CONSOLIDADO!$B$15 -> 65239649 | S10: =CONSOLIDADO!$B$14*CONSOLIDADO!$B$15 -> 3724959.1 | T10: =N10+O10+P10+Q10+R10+S10 -> 1.0431017e+09
A11: Julio | B11: ='DEMANDA BANXICO 2025'!B11*1000000 -> 27068004 | C11: ='DEMANDA BANXICO 2025'!C11*1000000 -> 31622993 | D11: ='DEMANDA BANXICO 2025'!D11*1000000 -> 17842520 | E11: ='DEMANDA BANXICO 2025'!E11*1000000 -> 38325.701 | F11: ='DEMANDA BANXICO 2025'!F11*1000000 -> 28709851 | G11: ='DEMANDA BANXICO 2025'!G11*1000000 -> 3363102.6 | H11: =SUM(B11:G11) -> 1.086448e+08 | I11: =B11*$B$25+C11*$C$25+D11*$D$25+E11*$E$25+F11*$F$25+G11*$G$25 -> 2617208.6 | J11: =B11*$B$28+C11*$C$28+D11*$D$28+E11*$E$28+F11*$F$28+G11*$G$28 -> 4197086.5 | K11: =SUMPRODUCT(B11:G11,'METALES 2025 BUENO'!B124:G124) -> 27687239 | L11: =SUMPRODUCT(B11:G11,'METALES 2025 BUENO'!B54:G54) -> 3.8708431e+08 | M11: =SUMPRODUCT(B11:G11,'METALES 2025 BUENO'!B96:G96) -> 44330126 | N11: =SUM(I11:M11) -> 4.6591597e+08 | O11: =CONSOLIDADO!$B$11 -> 37953243 | P11: =CONSOLIDADO!$B$12 -> 22051466 | Q11: =H11*CONSOLIDADO!$B$9 -> 896589 | R11: =CONSOLIDADO!$B$13*CONSOLIDADO!$B$15 -> 65239649 | S11: =CONSOLIDADO!$B$14*CONSOLIDADO!$B$15 -> 3724959.1 | T11: =N11+O11+P11+Q11+R11+S11 -> 5.9578188e+08
A12: Agosto | B12: ='DEMANDA BANXICO 2025'!B12*1000000 -> 77588191 | C12: ='DEMANDA BANXICO 2025'!C12*1000000 -> 72601882 | D12: ='DEMANDA BANXICO 2025'!D12*1000000 -> 45764991 | E12: ='DEMANDA BANXICO 2025'!E12*1000000 -> 49007603 | F12: ='DEMANDA BANXICO 2025'!F12*1000000 -> 18404680 | G12: ='DEMANDA BANXICO 2025'!G12*1000000 -> 4182060.5 | H12: =SUM(B12:G12) -> 2.6754941e+08 | I12: =B12*$B$25+C12*$C$25+D12*$D$25+E12*$E$25+F12*$F$25+G12*$G$25 -> 5837592.7 | J12: =B12*$B$28+C12*$C$28+D12*$D$28+E12*$E$28+F12*$F$28+G12*$G$28 -> 7398985.7 | K12: =SUMPRODUCT(B12:G12,'METALES 2025 BUENO'!B125:G125) -> 1.0216749e+08 | L12: =SUMPRODUCT(B12:G12,'METALES 2025 BUENO'!B55:G55) -> 6.2885169e+08 | M12: =SUMPRODUCT(B12:G12,'METALES 2025 BUENO'!B97:G97) -> 31657125 | N12: =SUM(I12:M12) -> 7.7591288e+08 | O12: =CONSOLIDADO!$B$11 -> 37953243 | P12: =CONSOLIDADO!$B$12 -> 22051466 | Q12: =H12*CONSOLIDADO!$B$9 -> 2207946.1 | R12: =CONSOLIDADO!$B$13*CONSOLIDADO!$B$15 -> 65239649 | S12: =CONSOLIDADO!$B$14*CONSOLIDADO!$B$15 -> 3724959.1 | T12: =N12+O12+P12+Q12+R12+S12 -> 9.0709015e+08
A13: Septiembre | B13: ='DEMANDA BANXICO 2025'!B13*1000000 -> 56343805 | C13: ='DEMANDA BANXICO 2025'!C13*1000000 -> 1.0952512e+08 | D13: ='DEMANDA BANXICO 2025'!D13*1000000 -> 53392489 | E13: ='DEMANDA BANXICO 2025'!E13*1000000 -> 43204071 | F13: ='DEMANDA BANXICO 2025'!F13*1000000 -> 26385470 | G13: ='DEMANDA BANXICO 2025'!G13*1000000 -> 2454836.9 | H13: =SUM(B13:G13) -> 2.913058e+08 | I13: =B13*$B$25+C13*$C$25+D13*$D$25+E13*$E$25+F13*$F$25+G13*$G$25 -> 6018700.4 | J13: =B13*$B$28+C13*$C$28+D13*$D$28+E13*$E$28+F13*$F$28+G13*$G$28 -> 8141089.4 | K13: =SUMPRODUCT(B13:G13,'METALES 2025 BUENO'!B126:G126) -> 1.0867595e+08 | L13: =SUMPRODUCT(B13:G13,'METALES 2025 BUENO'!B56:G56) -> 7.4793926e+08 | M13: =SUMPRODUCT(B13:G13,'METALES 2025 BUENO'!B98:G98) -> 39848985 | N13: =SUM(I13:M13) -> 9.1062398e+08 | O13: =CONSOLIDADO!$B$11 -> 37953243 | P13: =CONSOLIDADO!$B$12 -> 22051466 | Q13: =H13*CONSOLIDADO!$B$9 -> 2403995.2 | R13: =CONSOLIDADO!$B$13*CONSOLIDADO!$B$15 -> 65239649 | S13: =CONSOLIDADO!$B$14*CONSOLIDADO!$B$15 -> 3724959.1 | T13: =N13+O13+P13+Q13+R13+S13 -> 1.0419973e+09
A14: Octubre | B14: ='DEMANDA BANXICO 2025'!B14*1000000 -> 77008492 | C14: ='DEMANDA BANXICO 2025'!C14*1000000 -> 76669291 | D14: ='DEMANDA BANXICO 2025'!D14*1000000 -> 43991205 | E14: ='DEMANDA BANXICO 2025'!E14*1000000 -> 30082786 | F14: ='DEMANDA BANXICO 2025'!F14*1000000 -> 10230047 | G14: ='DEMANDA BANXICO 2025'!G14*1000000 -> 2335739.9 | H14: =SUM(B14:G14) -> 2.4031756e+08 | I14: =B14*$B$25+C14*$C$25+D14*$D$25+E14*$E$25+F14*$F$25+G14*$G$25 -> 5035649.5 | J14: =B14*$B$28+C14*$C$28+D14*$D$28+E14*$E$28+F14*$F$28+G14*$G$28 -> 5707337.5 | K14: =SUMPRODUCT(B14:G14,'METALES 2025 BUENO'!B127:G127) -> 90322381 | L14: =SUMPRODUCT(B14:G14,'METALES 2025 BUENO'!B57:G57) -> 4.7696664e+08 | M14: =SUMPRODUCT(B14:G14,'METALES 2025 BUENO'!B99:G99) -> 17662953 | N14: =SUM(I14:M14) -> 5.9569497e+08 | O14: =CONSOLIDADO!$B$11 -> 37953243 | P14: =CONSOLIDADO!$B$12 -> 22051466 | Q14: =H14*CONSOLIDADO!$B$9 -> 1983215.8 | R14: =CONSOLIDADO!$B$13*CONSOLIDADO!$B$15 -> 65239649 | S14: =CONSOLIDADO!$B$14*CONSOLIDADO!$B$15 -> 3724959.1 | T14: =N14+O14+P14+Q14+R14+S14 -> 7.266475e+08
A15: Noviembre | B15: ='DEMANDA BANXICO 2025'!B15*1000000 -> 63643382 | C15: ='DEMANDA BANXICO 2025'!C15*1000000 -> 84026445 | D15: ='DEMANDA BANXICO 2025'!D15*1000000 -> 46560034 | E15: ='DEMANDA BANXICO 2025'!E15*1000000 -> 29879524 | F15: ='DEMANDA BANXICO 2025'!F15*1000000 -> 34980159 | G15: ='DEMANDA BANXICO 2025'!G15*1000000 -> 3008749.7 | H15: =SUM(B15:G15) -> 2.6209829e+08 | I15: =B15*$B$25+C15*$C$25+D15*$D$25+E15*$E$25+F15*$F$25+G15*$G$25 -> 5545533.8 | J15: =B15*$B$28+C15*$C$28+D15*$D$28+E15*$E$28+F15*$F$28+G15*$G$28 -> 7777018.6 | K15: =SUMPRODUCT(B15:G15,'METALES 2025 BUENO'!B128:G128) -> 90000651 | L15: =SUMPRODUCT(B15:G15,'METALES 2025 BUENO'!B58:G58) -> 7.1506693e+08 | M15: =SUMPRODUCT(B15:G15,'METALES 2025 BUENO'!B100:G100) -> 52586375 | N15: =SUM(I15:M15) -> 8.7097651e+08 | O15: =CONSOLIDADO!$B$11 -> 37953243 | P15: =CONSOLIDADO!$B$12 -> 22051466 | Q15: =H15*CONSOLIDADO!$B$9 -> 2162960.9 | R15: =CONSOLIDADO!$B$13*CONSOLIDADO!$B$15 -> 65239649 | S15: =CONSOLIDADO!$B$14*CONSOLIDADO!$B$15 -> 3724959.1 | T15: =N15+O15+P15+Q15+R15+S15 -> 1.0021088e+09
A16: Diciembre | B16: ='DEMANDA BANXICO 2025'!B16*1000000 -> 20348126 | C16: ='DEMANDA BANXICO 2025'!C16*1000000 -> 53054264 | D16: ='DEMANDA BANXICO 2025'!D16*1000000 -> 26448761 | E16: ='DEMANDA BANXICO 2025'!E16*1000000 -> 32287690 | F16: ='DEMANDA BANXICO 2025'!F16*1000000 -> 28289794 | G16: ='DEMANDA BANXICO 2025'!G16*1000000 -> 4655510.5 | H16: =SUM(B16:G16) -> 1.6508415e+08 | I16: =B16*$B$25+C16*$C$25+D16*$D$25+E16*$E$25+F16*$F$25+G16*$G$25 -> 3892318.3 | J16: =B16*$B$28+C16*$C$28+D16*$D$28+E16*$E$28+F16*$F$28+G16*$G$28 -> 6252805.6 | K16: =SUMPRODUCT(B16:G16,'METALES 2025 BUENO'!B129:G129) -> 58207639 | L16: =SUMPRODUCT(B16:G16,'METALES 2025 BUENO'!B59:G59) -> 5.7431488e+08 | M16: =SUMPRODUCT(B16:G16,'METALES 2025 BUENO'!B101:G101) -> 46116068 | N16: =SUM(I16:M16) -> 6.8878371e+08 | O16: =CONSOLIDADO!$B$11 -> 37953243 | P16: =CONSOLIDADO!$B$12 -> 22051466 | Q16: =H16*CONSOLIDADO!$B$9 -> 1362353.6 | R16: =CONSOLIDADO!$B$13*CONSOLIDADO!$B$15 -> 65239649 | S16: =CONSOLIDADO!$B$14*CONSOLIDADO!$B$15 -> 3724959.1 | T16: =N16+O16+P16+Q16+R16+S16 -> 8.1911538e+08
A17: TOTAL ANUAL | B17: =SUM(B5:B16) -> 6.44e+08 | C17: =SUM(C5:C16) -> 8.55e+08 | D17: =SUM(D5:D16) -> 468000000 | E17: =SUM(E5:E16) -> 369000000 | F17: =SUM(F5:F16) -> 294000000 | G17: =SUM(G5:G16) -> 40000000 | H17: =SUM(H5:H16) -> 2.67e+09 | I17: =SUM(I5:I16) -> 57894006 | ... T17: =SUM(T5:T16) -> 1.0173318e+10
A21: TARIFAS UNITARIAS — ACUÑACIÓN Y COSPELEO | I21: CONTROL DE MODELO • Acuñación y cospeleo: se eliminó el factor 1.16 que estaba mezclado con inflación. • Libranza = Acuñación + Cospeleo + Acero + Bronce-Al + Alpaca. • El TOTAL no vuelve a sumar Acuñación ni Cospeleo. • Energía = piezas × costo unitario actualizado +15%. • Fijos = base mensual × 1.0396. • Bronce-Al y Alpaca usan los valores exactos almacenados en el archivo legado; los vínculos externos fueron eliminados. | J21: CONTROL DE MODELO • Acuñación y cospeleo: se eliminó el factor 1.16 que estaba mezclado con inflación. • Libranza = Acuñación + Cospeleo + Acero + Bronce-Al + Alpaca. • El TOTAL no vuelve a sumar Acuñación ni Cospeleo. • Energía = piezas × costo unitario actualizado +15%. • Fijos = base mensual × 1.0396. • Bronce-Al y Alpaca usan los valores exactos almacenados en el archivo legado; los vínculos externos fueron eliminados. | K21: CONTROL DE MODELO • Acuñación y cospeleo: se eliminó el factor 1.16 que estaba mezclado con inflación. • Libranza = Acuñación + Cospeleo + Acero + Bronce-Al + Alpaca. • El TOTAL no vuelve a sumar Acuñación ni Cospeleo. • Energía = piezas × costo unitario actualizado +15%. • Fijos = base mensual × 1.0396. • Bronce-Al y Alpaca usan los valores exactos almacenados en el archivo legado; los vínculos externos fueron eliminados. | L21: CONTROL DE MODELO • Acuñación y cospeleo: se eliminó el factor 1.16 que estaba mezclado con inflación. • Libranza = Acuñación + Cospeleo + Acero + Bronce-Al + Alpaca. • El TOTAL no vuelve a sumar Acuñación ni Cospeleo. • Energía = piezas × costo unitario actualizado +15%. • Fijos = base mensual × 1.0396. • Bronce-Al y Alpaca usan los valores exactos almacenados en el archivo legado; los vínculos externos fueron eliminados. | M21: CONTROL DE MODELO • Acuñación y cospeleo: se eliminó el factor 1.16 que estaba mezclado con inflación. • Libranza = Acuñación + Cospeleo + Acero + Bronce-Al + Alpaca. • El TOTAL no vuelve a sumar Acuñación ni Cospeleo. • Energía = piezas × costo unitario actualizado +15%. • Fijos = base mensual × 1.0396. • Bronce-Al y Alpaca usan los valores exactos almacenados en el archivo legado; los vínculos externos fueron eliminados. | N21: CONTROL DE MODELO • Acuñación y cospeleo: se eliminó el factor 1.16 que estaba mezclado con inflación. • Libranza = Acuñación + Cospeleo + Acero + Bronce-Al + Alpaca. • El TOTAL no vuelve a sumar Acuñación ni Cospeleo. • Energía = piezas × costo unitario actualizado +15%. • Fijos = base mensual × 1.0396. • Bronce-Al y Alpaca usan los valores exactos almacenados en el archivo legado; los vínculos externos fueron eliminados. | O21: CONTROL DE MODELO • Acuñación y cospeleo: se mantienen integrados una sola vez en Libranza. • K:M se calculan desde las tarifas unitarias centralizadas en METALES 2025. • METALES 2025 documenta pronósticos A–D, premios, composición y valor de Bronce-Al/Alpaca. • Acero: se documenta precio base + sobrecargo como referencia; las tarifas presupuestales se conservan hasta validar la fórmula contractual completa. | P21: CONTROL DE MODELO • Acuñación y cospeleo: se eliminó el factor 1.16 que estaba mezclado con inflación. • Libranza = Acuñación + Cospeleo + Acero + Bronce-Al + Alpaca. • El TOTAL no vuelve a sumar Acuñación ni Cospeleo. • Energía = piezas × costo unitario actualizado +15%. • Fijos = base mensual × 1.0396. • Bronce-Al y Alpaca usan los valores exactos almacenados en el archivo legado; los vínculos externos fueron eliminados. | Q21: CONTROL DE MODELO • Acuñación y cospeleo: se eliminó el factor 1.16 que estaba mezclado con inflación. • Libranza = Acuñación + Cospeleo + Acero + Bronce-Al + Alpaca. • El TOTAL no vuelve a sumar Acuñación ni Cospeleo. • Energía = piezas × costo unitario actualizado +15%. • Fijos = base mensual × 1.0396. • Bronce-Al y Alpaca usan los valores exactos almacenados en el archivo legado; los vínculos externos fueron eliminados. | R21: CONTROL DE MODELO • Acuñación y cospeleo: se eliminó el factor 1.16 que estaba mezclado con inflación. • Libranza = Acuñación + Cospeleo + Acero + Bronce-Al + Alpaca. • El TOTAL no vuelve a sumar Acuñación ni Cospeleo. • Energía = piezas × costo unitario actualizado +15%. • Fijos = base mensual × 1.0396. • Bronce-Al y Alpaca usan los valores exactos almacenados en el archivo legado; los vínculos externos fueron eliminados. | S21: CONTROL DE MODELO • Acuñación y cospeleo: se eliminó el factor 1.16 que estaba mezclado con inflación. • Libranza = Acuñación + Cospeleo + Acero + Bronce-Al + Alpaca. • El TOTAL no vuelve a sumar Acuñación ni Cospeleo. • Energía = piezas × costo unitario actualizado +15%. • Fijos = base mensual × 1.0396. • Bronce-Al y Alpaca usan los valores exactos almacenados en el archivo legado; los vínculos externos fueron eliminados. | T21: CONTROL DE MODELO • Acuñación y cospeleo: se eliminó el factor 1.16 que estaba mezclado con inflación. • Libranza = Acuñación + Cospeleo + Acero + Bronce-Al + Alpaca. • El TOTAL no vuelve a sumar Acuñación ni Cospeleo. • Energía = piezas × costo unitario actualizado +15%. • Fijos = base mensual × 1.0396. • Bronce-Al y Alpaca usan los valores exactos almacenados en el archivo legado; los vínculos externos fueron eliminados.
A22: Concepto | B22: $0.5 | C22: $1 | D22: $2 | E22: $5 | F22: $10 | G22: $20 | I22: CONTROL DE MODELO • Acuñación y cospeleo: se eliminó el factor 1.16 que estaba mezclado con inflación. • Libranza = Acuñación + Cospeleo + Acero + Bronce-Al + Alpaca. • El TOTAL no vuelve a sumar Acuñación ni Cospeleo. • Energía = piezas × costo unitario actualizado +15%. • Fijos = base mensual × 1.0396. • Bronce-Al y Alpaca usan los valores exactos almacenados en el archivo legado; los vínculos externos fueron eliminados. | J22: CONTROL DE MODELO • Acuñación y cospeleo: se eliminó el factor 1.16 que estaba mezclado con inflación. • Libranza = Acuñación + Cospeleo + Acero + Bronce-Al + Alpaca. • El TOTAL no vuelve a sumar Acuñación ni Cospeleo. • Energía = piezas × costo unitario actualizado +15%. • Fijos = base mensual × 1.0396. • Bronce-Al y Alpaca usan los valores exactos almacenados en el archivo legado; los vínculos externos fueron eliminados. | K22: CONTROL DE MODELO • Acuñación y cospeleo: se eliminó el factor 1.16 que estaba mezclado con inflación. • Libranza = Acuñación + Cospeleo + Acero + Bronce-Al + Alpaca. • El TOTAL no vuelve a sumar Acuñación ni Cospeleo. • Energía = piezas × costo unitario actualizado +15%. • Fijos = base mensual × 1.0396. • Bronce-Al y Alpaca usan los valores exactos almacenados en el archivo legado; los vínculos externos fueron eliminados. | L22: CONTROL DE MODELO • Acuñación y cospeleo: se eliminó el factor 1.16 que estaba mezclado con inflación. • Libranza = Acuñación + Cospeleo + Acero + Bronce-Al + Alpaca. • El TOTAL no vuelve a sumar Acuñación ni Cospeleo. • Energía = piezas × costo unitario actualizado +15%. • Fijos = base mensual × 1.0396. • Bronce-Al y Alpaca usan los valores exactos almacenados en el archivo legado; los vínculos externos fueron eliminados. | M22: CONTROL DE MODELO • Acuñación y cospeleo: se eliminó el factor 1.16 que estaba mezclado con inflación. • Libranza = Acuñación + Cospeleo + Acero + Bronce-Al + Alpaca. • El TOTAL no vuelve a sumar Acuñación ni Cospeleo. • Energía = piezas × costo unitario actualizado +15%. • Fijos = base mensual × 1.0396. • Bronce-Al y Alpaca usan los valores exactos almacenados en el archivo legado; los vínculos externos fueron eliminados. | N22: CONTROL DE MODELO • Acuñación y cospeleo: se eliminó el factor 1.16 que estaba mezclado con inflación. • Libranza = Acuñación + Cospeleo + Acero + Bronce-Al + Alpaca. • El TOTAL no vuelve a sumar Acuñación ni Cospeleo. • Energía = piezas × costo unitario actualizado +15%. • Fijos = base mensual × 1.0396. • Bronce-Al y Alpaca usan los valores exactos almacenados en el archivo legado; los vínculos externos fueron eliminados. | O22: CONTROL DE MODELO • Acuñación y cospeleo: se eliminó el factor 1.16 que estaba mezclado con inflación. • Libranza = Acuñación + Cospeleo + Acero + Bronce-Al + Alpaca. • El TOTAL no vuelve a sumar Acuñación ni Cospeleo. • Energía = piezas × costo unitario actualizado +15%. • Fijos = base mensual × 1.0396. • Bronce-Al y Alpaca usan los valores exactos almacenados en el archivo legado; los vínculos externos fueron eliminados. | P22: CONTROL DE MODELO • Acuñación y cospeleo: se eliminó el factor 1.16 que estaba mezclado con inflación. • Libranza = Acuñación + Cospeleo + Acero + Bronce-Al + Alpaca. • El TOTAL no vuelve a sumar Acuñación ni Cospeleo. • Energía = piezas × costo unitario actualizado +15%. • Fijos = base mensual × 1.0396. • Bronce-Al y Alpaca usan los valores exactos almacenados en el archivo legado; los vínculos externos fueron eliminados. | Q22: CONTROL DE MODELO • Acuñación y cospeleo: se eliminó el factor 1.16 que estaba mezclado con inflación. • Libranza = Acuñación + Cospeleo + Acero + Bronce-Al + Alpaca. • El TOTAL no vuelve a sumar Acuñación ni Cospeleo. • Energía = piezas × costo unitario actualizado +15%. • Fijos = base mensual × 1.0396. • Bronce-Al y Alpaca usan los valores exactos almacenados en el archivo legado; los vínculos externos fueron eliminados. | R22: CONTROL DE MODELO • Acuñación y cospeleo: se eliminó el factor 1.16 que estaba mezclado con inflación. • Libranza = Acuñación + Cospeleo + Acero + Bronce-Al + Alpaca. • El TOTAL no vuelve a sumar Acuñación ni Cospeleo. • Energía = piezas × costo unitario actualizado +15%. • Fijos = base mensual × 1.0396. • Bronce-Al y Alpaca usan los valores exactos almacenados en el archivo legado; los vínculos externos fueron eliminados. | S22: CONTROL DE MODELO • Acuñación y cospeleo: se eliminó el factor 1.16 que estaba mezclado con inflación. • Libranza = Acuñación + Cospeleo + Acero + Bronce-Al + Alpaca. • El TOTAL no vuelve a sumar Acuñación ni Cospeleo. • Energía = piezas × costo unitario actualizado +15%. • Fijos = base mensual × 1.0396. • Bronce-Al y Alpaca usan los valores exactos almacenados en el archivo legado; los vínculos externos fueron eliminados. | T22: CONTROL DE MODELO • Acuñación y cospeleo: se eliminó el factor 1.16 que estaba mezclado con inflación. • Libranza = Acuñación + Cospeleo + Acero + Bronce-Al + Alpaca. • El TOTAL no vuelve a sumar Acuñación ni Cospeleo. • Energía = piezas × costo unitario actualizado +15%. • Fijos = base mensual × 1.0396. • Bronce-Al y Alpaca usan los valores exactos almacenados en el archivo legado; los vínculos externos fueron eliminados.
A23: Acuñación base 2024 | B23: 0.01925978 | C23: 0.01851129 | D23: 0.01851129 | E23: 0.01851129 | F23: 0.01851129 | G23: 0.16305031 | I23: CONTROL DE MODELO • Acuñación y cospeleo: se eliminó el factor 1.16 que estaba mezclado con inflación. • Libranza = Acuñación + Cospeleo + Acero + Bronce-Al + Alpaca. • El TOTAL no vuelve a sumar Acuñación ni Cospeleo. • Energía = piezas × costo unitario actualizado +15%. • Fijos = base mensual × 1.0396. • Bronce-Al y Alpaca usan los valores exactos almacenados en el archivo legado; los vínculos externos fueron eliminados. | J23: CONTROL DE MODELO • Acuñación y cospeleo: se eliminó el factor 1.16 que estaba mezclado con inflación. • Libranza = Acuñación + Cospeleo + Acero + Bronce-Al + Alpaca. • El TOTAL no vuelve a sumar Acuñación ni Cospeleo. • Energía = piezas × costo unitario actualizado +15%. • Fijos = base mensual × 1.0396. • Bronce-Al y Alpaca usan los valores exactos almacenados en el archivo legado; los vínculos externos fueron eliminados. | K23: CONTROL DE MODELO • Acuñación y cospeleo: se eliminó el factor 1.16 que estaba mezclado con inflación. • Libranza = Acuñación + Cospeleo + Acero + Bronce-Al + Alpaca. • El TOTAL no vuelve a sumar Acuñación ni Cospeleo. • Energía = piezas × costo unitario actualizado +15%. • Fijos = base mensual × 1.0396. • Bronce-Al y Alpaca usan los valores exactos almacenados en el archivo legado; los vínculos externos fueron eliminados. | L23: CONTROL DE MODELO • Acuñación y cospeleo: se eliminó el factor 1.16 que estaba mezclado con inflación. • Libranza = Acuñación + Cospeleo + Acero + Bronce-Al + Alpaca. • El TOTAL no vuelve a sumar Acuñación ni Cospeleo. • Energía = piezas × costo unitario actualizado +15%. • Fijos = base mensual × 1.0396. • Bronce-Al y Alpaca usan los valores exactos almacenados en el archivo legado; los vínculos externos fueron eliminados. | M23: CONTROL DE MODELO • Acuñación y cospeleo: se eliminó el factor 1.16 que estaba mezclado con inflación. • Libranza = Acuñación + Cospeleo + Acero + Bronce-Al + Alpaca. • El TOTAL no vuelve a sumar Acuñación ni Cospeleo. • Energía = piezas × costo unitario actualizado +15%. • Fijos = base mensual × 1.0396. • Bronce-Al y Alpaca usan los valores exactos almacenados en el archivo legado; los vínculos externos fueron eliminados. | N23: CONTROL DE MODELO • Acuñación y cospeleo: se eliminó el factor 1.16 que estaba mezclado con inflación. • Libranza = Acuñación + Cospeleo + Acero + Bronce-Al + Alpaca. • El TOTAL no vuelve a sumar Acuñación ni Cospeleo. • Energía = piezas × costo unitario actualizado +15%. • Fijos = base mensual × 1.0396. • Bronce-Al y Alpaca usan los valores exactos almacenados en el archivo legado; los vínculos externos fueron eliminados. | O23: CONTROL DE MODELO • Acuñación y cospeleo: se eliminó el factor 1.16 que estaba mezclado con inflación. • Libranza = Acuñación + Cospeleo + Acero + Bronce-Al + Alpaca. • El TOTAL no vuelve a sumar Acuñación ni Cospeleo. • Energía = piezas × costo unitario actualizado +15%. • Fijos = base mensual × 1.0396. • Bronce-Al y Alpaca usan los valores exactos almacenados en el archivo legado; los vínculos externos fueron eliminados. | P23: CONTROL DE MODELO • Acuñación y cospeleo: se eliminó el factor 1.16 que estaba mezclado con inflación. • Libranza = Acuñación + Cospeleo + Acero + Bronce-Al + Alpaca. • El TOTAL no vuelve a sumar Acuñación ni Cospeleo. • Energía = piezas × costo unitario actualizado +15%. • Fijos = base mensual × 1.0396. • Bronce-Al y Alpaca usan los valores exactos almacenados en el archivo legado; los vínculos externos fueron eliminados. | Q23: CONTROL DE MODELO • Acuñación y cospeleo: se eliminó el factor 1.16 que estaba mezclado con inflación. • Libranza = Acuñación + Cospeleo + Acero + Bronce-Al + Alpaca. • El TOTAL no vuelve a sumar Acuñación ni Cospeleo. • Energía = piezas × costo unitario actualizado +15%. • Fijos = base mensual × 1.0396. • Bronce-Al y Alpaca usan los valores exactos almacenados en el archivo legado; los vínculos externos fueron eliminados. | R23: CONTROL DE MODELO • Acuñación y cospeleo: se eliminó el factor 1.16 que estaba mezclado con inflación. • Libranza = Acuñación + Cospeleo + Acero + Bronce-Al + Alpaca. • El TOTAL no vuelve a sumar Acuñación ni Cospeleo. • Energía = piezas × costo unitario actualizado +15%. • Fijos = base mensual × 1.0396. • Bronce-Al y Alpaca usan los valores exactos almacenados en el archivo legado; los vínculos externos fueron eliminados. | S23: CONTROL DE MODELO • Acuñación y cospeleo: se eliminó el factor 1.16 que estaba mezclado con inflación. • Libranza = Acuñación + Cospeleo + Acero + Bronce-Al + Alpaca. • El TOTAL no vuelve a sumar Acuñación ni Cospeleo. • Energía = piezas × costo unitario actualizado +15%. • Fijos = base mensual × 1.0396. • Bronce-Al y Alpaca usan los valores exactos almacenados en el archivo legado; los vínculos externos fueron eliminados. | T23: CONTROL DE MODELO • Acuñación y cospeleo: se eliminó el factor 1.16 que estaba mezclado con inflación. • Libranza = Acuñación + Cospeleo + Acero + Bronce-Al + Alpaca. • El TOTAL no vuelve a sumar Acuñación ni Cospeleo. • Energía = piezas × costo unitario actualizado +15%. • Fijos = base mensual × 1.0396. • Bronce-Al y Alpaca usan los valores exactos almacenados en el archivo legado; los vínculos externos fueron eliminados.
A24: Factor inflación | B24: =CONSOLIDADO!$B$5 -> 1.0396 | C24: =CONSOLIDADO!$B$5 -> 1.0396 | D24: =CONSOLIDADO!$B$5 -> 1.0396 | E24: =CONSOLIDADO!$B$5 -> 1.0396 | F24: =CONSOLIDADO!$B$5 -> 1.0396 | G24: =CONSOLIDADO!$B$5 -> 1.0396 | I24: CONTROL DE MODELO • Acuñación y cospeleo: se eliminó el factor 1.16 que estaba mezclado con inflación. • Libranza = Acuñación + Cospeleo + Acero + Bronce-Al + Alpaca. • El TOTAL no vuelve a sumar Acuñación ni Cospeleo. • Energía = piezas × costo unitario actualizado +15%. • Fijos = base mensual × 1.0396. • Bronce-Al y Alpaca usan los valores exactos almacenados en el archivo legado; los vínculos externos fueron eliminados. | J24: CONTROL DE MODELO • Acuñación y cospeleo: se eliminó el factor 1.16 que estaba mezclado con inflación. • Libranza = Acuñación + Cospeleo + Acero + Bronce-Al + Alpaca. • El TOTAL no vuelve a sumar Acuñación ni Cospeleo. • Energía = piezas × costo unitario actualizado +15%. • Fijos = base mensual × 1.0396. • Bronce-Al y Alpaca usan los valores exactos almacenados en el archivo legado; los vínculos externos fueron eliminados. | K24: CONTROL DE MODELO • Acuñación y cospeleo: se eliminó el factor 1.16 que estaba mezclado con inflación. • Libranza = Acuñación + Cospeleo + Acero + Bronce-Al + Alpaca. • El TOTAL no vuelve a sumar Acuñación ni Cospeleo. • Energía = piezas × costo unitario actualizado +15%. • Fijos = base mensual × 1.0396. • Bronce-Al y Alpaca usan los valores exactos almacenados en el archivo legado; los vínculos externos fueron eliminados. | L24: CONTROL DE MODELO • Acuñación y cospeleo: se eliminó el factor 1.16 que estaba mezclado con inflación. • Libranza = Acuñación + Cospeleo + Acero + Bronce-Al + Alpaca. • El TOTAL no vuelve a sumar Acuñación ni Cospeleo. • Energía = piezas × costo unitario actualizado +15%. • Fijos = base mensual × 1.0396. • Bronce-Al y Alpaca usan los valores exactos almacenados en el archivo legado; los vínculos externos fueron eliminados. | M24: CONTROL DE MODELO • Acuñación y cospeleo: se eliminó el factor 1.16 que estaba mezclado con inflación. • Libranza = Acuñación + Cospeleo + Acero + Bronce-Al + Alpaca. • El TOTAL no vuelve a sumar Acuñación ni Cospeleo. • Energía = piezas × costo unitario actualizado +15%. • Fijos = base mensual × 1.0396. • Bronce-Al y Alpaca usan los valores exactos almacenados en el archivo legado; los vínculos externos fueron eliminados. | N24: CONTROL DE MODELO • Acuñación y cospeleo: se eliminó el factor 1.16 que estaba mezclado con inflación. • Libranza = Acuñación + Cospeleo + Acero + Bronce-Al + Alpaca. • El TOTAL no vuelve a sumar Acuñación ni Cospeleo. • Energía = piezas × costo unitario actualizado +15%. • Fijos = base mensual × 1.0396. • Bronce-Al y Alpaca usan los valores exactos almacenados en el archivo legado; los vínculos externos fueron eliminados. | O24: CONTROL DE MODELO • Acuñación y cospeleo: se eliminó el factor 1.16 que estaba mezclado con inflación. • Libranza = Acuñación + Cospeleo + Acero + Bronce-Al + Alpaca. • El TOTAL no vuelve a sumar Acuñación ni Cospeleo. • Energía = piezas × costo unitario actualizado +15%. • Fijos = base mensual × 1.0396. • Bronce-Al y Alpaca usan los valores exactos almacenados en el archivo legado; los vínculos externos fueron eliminados. | P24: CONTROL DE MODELO • Acuñación y cospeleo: se eliminó el factor 1.16 que estaba mezclado con inflación. • Libranza = Acuñación + Cospeleo + Acero + Bronce-Al + Alpaca. • El TOTAL no vuelve a sumar Acuñación ni Cospeleo. • Energía = piezas × costo unitario actualizado +15%. • Fijos = base mensual × 1.0396. • Bronce-Al y Alpaca usan los valores exactos almacenados en el archivo legado; los vínculos externos fueron eliminados. | Q24: CONTROL DE MODELO • Acuñación y cospeleo: se eliminó el factor 1.16 que estaba mezclado con inflación. • Libranza = Acuñación + Cospeleo + Acero + Bronce-Al + Alpaca. • El TOTAL no vuelve a sumar Acuñación ni Cospeleo. • Energía = piezas × costo unitario actualizado +15%. • Fijos = base mensual × 1.0396. • Bronce-Al y Alpaca usan los valores exactos almacenados en el archivo legado; los vínculos externos fueron eliminados. | R24: CONTROL DE MODELO • Acuñación y cospeleo: se eliminó el factor 1.16 que estaba mezclado con inflación. • Libranza = Acuñación + Cospeleo + Acero + Bronce-Al + Alpaca. • El TOTAL no vuelve a sumar Acuñación ni Cospeleo. • Energía = piezas × costo unitario actualizado +15%. • Fijos = base mensual × 1.0396. • Bronce-Al y Alpaca usan los valores exactos almacenados en el archivo legado; los vínculos externos fueron eliminados. | S24: CONTROL DE MODELO • Acuñación y cospeleo: se eliminó el factor 1.16 que estaba mezclado con inflación. • Libranza = Acuñación + Cospeleo + Acero + Bronce-Al + Alpaca. • El TOTAL no vuelve a sumar Acuñación ni Cospeleo. • Energía = piezas × costo unitario actualizado +15%. • Fijos = base mensual × 1.0396. • Bronce-Al y Alpaca usan los valores exactos almacenados en el archivo legado; los vínculos externos fueron eliminados. | T24: CONTROL DE MODELO • Acuñación y cospeleo: se eliminó el factor 1.16 que estaba mezclado con inflación. • Libranza = Acuñación + Cospeleo + Acero + Bronce-Al + Alpaca. • El TOTAL no vuelve a sumar Acuñación ni Cospeleo. • Energía = piezas × costo unitario actualizado +15%. • Fijos = base mensual × 1.0396. • Bronce-Al y Alpaca usan los valores exactos almacenados en el archivo legado; los vínculos externos fueron eliminados.
A25: Acuñación 2025 corregida | B25: =B23*B24 -> 0.020022467 | C25: =C23*C24 -> 0.019244337 | D25: =D23*D24 -> 0.019244337 | E25: =E23*E24 -> 0.019244337 | F25: =F23*F24 -> 0.019244337 | G25: =G23*G24 -> 0.1695071
A26: Cospeleo base 2024 | B26: 0.00783227 | C26: 0.01923056 | D26: 0.02515134 | E26: 0.03558049 | F26: 0.07066377 | G26: 0.21950203
A27: Factor inflación | B27: =CONSOLIDADO!$B$5 -> 1.0396 | C27: =CONSOLIDADO!$B$5 -> 1.0396 | D27: =CONSOLIDADO!$B$5 -> 1.0396 | E27: =CONSOLIDADO!$B$5 -> 1.0396 | F27: =CONSOLIDADO!$B$5 -> 1.0396 | G27: =CONSOLIDADO!$B$5 -> 1.0396
A28: Cospeleo 2025 corregido | B28: =B26*B27 -> 0.0081424279 | C28: =C26*C27 -> 0.01999209 | D28: =D26*D27 -> 0.026147333 | E28: =E26*E27 -> 0.036989477 | F28: =F26*F27 -> 0.073462055 | G28: =G26*G27 -> 0.22819431

Sheet DEMANDA BANXICO 2025
A1: ESTIMACIÓN CALENDARIZADA DE DEMANDA BANXICO 2025
A2: Fuente: ESTIMACIONCALENDARIZADADEMANDA2025BANXICOCURSOLEGAL2670millonesm20 045 2024 BANXICOCESCENARIOFUTUROSmasIVA TC 19.36.xls
A4: Mes | B4: $0.50 | C4: $1.00 | D4: $2.00 | E4: $5.00 | F4: $10.00 | G4: $20.00 | H4: Total (millones)
A5: Enero | B5: 83.218841 | C5: 35.917078 | D5: 16.142802 | E5: 35.247076 | F5: 19.523042 | G5: 3.144678 | H5: 193.19352
A6: Febrero | B6: 77.781159 | C6: 81.504139 | D6: 32.135872 | E6: 32.669918 | F6: 29.540101 | G6: 4.7336115 | H6: 258.3648
A7: Marzo | B7: 0 | C7: 96.328782 | D7: 68.721326 | E7: 24.333006 | F7: 24.436857 | G7: 2.1217105 | H7: 215.94168
A8: Abril | B8: 63.699295 | C8: 37.436387 | D8: 24.554395 | E8: 24.956358 | F8: 14.12929 | G8: 1.0793786 | H8: 165.85511
A9: Mayo | B9: 97.270545 | C9: 80.807812 | D9: 64.673372 | E9: 30.108668 | F9: 20.662341 | G9: 3.7778252 | H9: 297.30056
A10: Junio | B10: 0.030159608 | C10: 95.505801 | D10: 27.772233 | E10: 37.184974 | F10: 38.708369 | G10: 5.1427961 | H10: 204.34433
A11: Julio | B11: 27.068004 | C11: 31.622993 | D11: 17.84252 | E11: 0.038325701 | F11: 28.709851 | G11: 3.3631026 | H11: 108.6448
A12: Agosto | B12: 77.588191 | C12: 72.601882 | D12: 45.764991 | E12: 49.007603 | F12: 18.40468 | G12: 4.1820605 | H12: 267.54941
A13: Septiembre | B13: 56.343805 | C13: 109.52512 | D13: 53.392489 | E13: 43.204071 | F13: 26.38547 | G13: 2.4548369 | H13: 291.3058
A14: Octubre | B14: 77.008492 | C14: 76.669291 | D14: 43.991205 | E14: 30.082786 | F14: 10.230047 | G14: 2.3357399 | H14: 240.31756
A15: Noviembre | B15: 63.643382 | C15: 84.026445 | D15: 46.560034 | E15: 29.879524 | F15: 34.980159 | G15: 3.0087497 | H15: 262.09829
A16: Diciembre | B16: 20.348126 | C16: 53.054264 | D16: 26.448761 | E16: 32.28769 | F16: 28.289794 | G16: 4.6555105 | H16: 165.08415
A17: TOTAL ANUAL | B17: =SUM(B5:B16) -> 644 | C17: =SUM(C5:C16) -> 855 | D17: =SUM(D5:D16) -> 468 | E17: =SUM(E5:E16) -> 369 | F17: =SUM(F5:F16) -> 294 | G17: =SUM(G5:G16) -> 40 | H17: =SUM(H5:H16) -> 2670
A20: Supuesto fuente | B20: Valor | C20: Unidad / comentario | D20: Tratamiento en modelo reconstruido
A21: Tipo de cambio | B21: 19.36 | C21: MXN/USD | D21: Se fija en 19.36 en todo el modelo
A22: Volumen anual | B22: 2670 | C22: millones de piezas | D22: Se conserva
A23: Distribución mensual | B23: Distribución 2024 | C23: Nota del archivo fuente | D23: Se conserva
A24: Distribución trimestral | B24: Anual / 4 | C24: Nota del archivo fuente | D24: Se conserva
A25: Hoja fuente utilizada | B25: Estimado Producción 2025 | C25: Del segundo .xls | D25: Base para las piezas por denominación
A28: REQUERIMIENTOS / SUPUESTOS TÉCNICOS PRESENTES EN EL ARCHIVO FUENTE
A29: Concepto | B29: 10¢ / acero | C29: $1 ari | D29: $2 ari | E29: $5 ari | F29: 50¢ / bronce | G29: $1 nuc
A30: % scrap / indicador fuente | B30: 1 | C30: 0.59 | D30: 0.597 | E30: 0.602 | F30: 0.284 | G30: 0.269
A31: Gramos por pieza | C31: 5.2195122 | D31: 6.9727047 | E31: 9.5979899 | F31: 4.3337989 | G31: 2.4760602
A32: Rendimiento producción | C32: 0.41 | D32: 0.403 | E32: 0.398 | F32: 0.716 | G32: 0.731
A33: Observación | B33: Valores copiados como datos | C33: del archivo | D33: fuente; no se | E33: usan directamente | F33: en el total | G33: del presupuesto

Sheet METALES 2025 BUENO
A1: METALES 2025 BUENO — FORMACIÓN DE VALORES Y TARIFAS
A2: Hoja fuente para MESES 2025. Sin factores de homologación y sin celdas combinadas.
A4: SUPUESTO | B4: VALOR | C4: UNIDAD | D4: FUENTE / CRITERIO
A5: Tipo de cambio | B5: 19.36 | C5: MXN/USD | D5: Fijo 2025
A6: FAA / IVA | B6: 0.16 | C6: % | D6: EJEMPLO ENERO 2
A7: Recuperación de scrap | B7: 0.93 | C7: % | D7: EJEMPLO ENERO 2
A8: Inflación | B8: 0.0396 | C8: % anual | D8: Presupuesto 2025
A10: PRONÓSTICOS MENSUALES DE METALES — INSUMOS A–D
A11: METAL | B11: BASE | C11: ENERO | D11: FEBRERO | E11: MARZO | F11: ABRIL | G11: MAYO | H11: JUNIO | I11: JULIO | J11: AGOSTO | K11: SEPTIEMBRE | L11: OCTUBRE | M11: NOVIEMBRE | N11: DICIEMBRE
A12: COBRE | B12: 8.9030633 | C12: 8.9030633 | D12: 8.9186779 | E12: 8.9417112 | F12: 8.9664599 | G12: 8.9916052 | H12: 9.0168422 | I12: 9.0421003 | J12: 9.0673634 | K12: 9.0926276 | L12: 9.1178921 | M12: 9.1431566 | N12: 9.1684212
A13: ALUMINIO | B13: 2.5445576 | C13: 2.5445576 | D13: 2.5506874 | E13: 2.5568172 | F13: 2.562947 | G13: 2.5690768 | H13: 2.5752066 | I13: 2.5813364 | J13: 2.5874662 | K13: 2.593596 | L13: 2.5997258 | M13: 2.6058556 | N13: 2.6119854
A14: NÍQUEL | B14: 15.47052 | C14: 15.47052 | D14: 15.47052 | E14: 15.47052 | F14: 15.47052 | G14: 15.47052 | H14: 15.47052 | I14: 15.47052 | J14: 15.47052 | K14: 15.47052 | L14: 15.47052 | M14: 15.47052 | N14: 15.47052
A15: ZINC | B15: 3.046564 | C15: 3.046564 | D15: 3.0479917 | E15: 3.0485642 | F15: 3.0487938 | G15: 3.0488858 | H15: 3.0489227 | I15: 3.0489375 | J15: 3.0489435 | K15: 3.0489458 | L15: 3.0489468 | M15: 3.0489472 | N15: 3.0489473
A18: BRONCE-ALUMINIO / NACOBRE — FORMACIÓN DEL VALOR Y TARIFAS
A19: PARÁMETRO | B19: VALOR | C19: UNIDAD | D19: FUENTE / CRITERIO
A20: Composición cobre | B20: 0.92 | C20: % | D20: Fijo
A21: Composición aluminio | B21: 0.06 | C21: % | D21: Fijo
A22: Composición níquel | B22: 0.02 | C22: % | D22: Fijo
A23: Premio cobre | B23: 0.188 | C23: USD/kg | D23: Fijo
A24: Premio aluminio | B24: 0.1279 | C24: % del precio Al | D24: Fijo
A25: Premio níquel | B25: 1.05 | C25: USD/kg | D25: Fijo
A26: Costo transformación | B26: 17.945803 | C26: USD/kg | D26: EJEMPLO ENERO 2
A27: Valor base enero aleación sin FAA | B27: 24.12342 | C27: USD/kg | D27: EJEMPLO ENERO 2
A29: CONCEPTO | B29: ENERO | C29: FEBRERO | D29: MARZO | E29: ABRIL | F29: MAYO | G29: JUNIO | H29: JULIO | I29: AGOSTO | J29: SEPTIEMBRE | K29: OCTUBRE | L29: NOVIEMBRE | M29: DICIEMBRE
A30: Componente Cu teórico | B30: =('METALES 2025 BUENO'!C$12+$B$23)*$B$20 -> 8.3637783 | C30: =('METALES 2025 BUENO'!D$12+$B$23)*$B$20 -> 8.3781436 | D30: =('METALES 2025 BUENO'!E$12+$B$23)*$B$20 -> 8.3993343 | E30: =('METALES 2025 BUENO'!F$12+$B$23)*$B$20 -> 8.4221031 | F30: =('METALES 2025 BUENO'!G$12+$B$23)*$B$20 -> 8.4452368 | G30: =('METALES 2025 BUENO'!H$12+$B$23)*$B$20 -> 8.4684548 | H30: =('METALES 2025 BUENO'!I$12+$B$23)*$B$20 -> 8.4916923 | I30: =('METALES 2025 BUENO'!J$12+$B$23)*$B$20 -> 8.5149343 | ... M30: =('METALES 2025 BUENO'!N$12+$B$23)*$B$20 -> 8.6079075
A31: Componente Al teórico | B31: =('METALES 2025 BUENO'!C$13+('METALES 2025 BUENO'!C$13*$B$24))*$B$21 -> 0.17220039 | C31: =('METALES 2025 BUENO'!D$13+('METALES 2025 BUENO'!D$13*$B$24))*$B$21 -> 0.17261522 | D31: =('METALES 2025 BUENO'!E$13+('METALES 2025 BUENO'!E$13*$B$24))*$B$21 -> 0.17303004 | E31: =('METALES 2025 BUENO'!F$13+('METALES 2025 BUENO'!F$13*$B$24))*$B$21 -> 0.17344487 | F31: =('METALES 2025 BUENO'!G$13+('METALES 2025 BUENO'!G$13*$B$24))*$B$21 -> 0.1738597 | G31: =('METALES 2025 BUENO'!H$13+('METALES 2025 BUENO'!H$13*$B$24))*$B$21 -> 0.17427453 | H31: =('METALES 2025 BUENO'!I$13+('METALES 2025 BUENO'!I$13*$B$24))*$B$21 -> 0.17468936 | I31: =('METALES 2025 BUENO'!J$13+('METALES 2025 BUENO'!J$13*$B$24))*$B$21 -> 0.17510418 | ... M31: =('METALES 2025 BUENO'!N$13+('METALES 2025 BUENO'!N$13*$B$24))*$B$21 -> 0.1767635
A32: Componente Ni teórico | B32: =('METALES 2025 BUENO'!C$14+$B$25)*$B$22 -> 0.3304104 | C32: =('METALES 2025 BUENO'!D$14+$B$25)*$B$22 -> 0.3304104 | D32: =('METALES 2025 BUENO'!E$14+$B$25)*$B$22 -> 0.3304104 | E32: =('METALES 2025 BUENO'!F$14+$B$25)*$B$22 -> 0.3304104 | F32: =('METALES 2025 BUENO'!G$14+$B$25)*$B$22 -> 0.3304104 | G32: =('METALES 2025 BUENO'!H$14+$B$25)*$B$22 -> 0.3304104 | H32: =('METALES 2025 BUENO'!I$14+$B$25)*$B$22 -> 0.3304104 | I32: =('METALES 2025 BUENO'!J$14+$B$25)*$B$22 -> 0.3304104 | ... M32: =('METALES 2025 BUENO'!N$14+$B$25)*$B$22 -> 0.3304104
A33: Índice teórico aleación | B33: =SUM(B30:B32) -> 8.8663891 | C33: =SUM(C30:C32) -> 8.8811693 | D33: =SUM(D30:D32) -> 8.9027748 | E33: =SUM(E30:E32) -> 8.9259584 | F33: =SUM(F30:F32) -> 8.9495069 | G33: =SUM(G30:G32) -> 8.9731397 | H33: =SUM(H30:H32) -> 8.9967921 | I33: =SUM(I30:I32) -> 9.0204489 | ... M33: =SUM(M30:M32) -> 9.1150814
A34: Variación vs enero | B34: =B33-$B$33 -> 0 | C34: =C33-$B$33 -> 0.014780208 | D34: =D33-$B$33 -> 0.036385732 | E34: =E33-$B$33 -> 0.059569342 | F34: =F33-$B$33 -> 0.083117824 | G34: =G33-$B$33 -> 0.10675067 | H34: =H33-$B$33 -> 0.13040302 | I34: =I33-$B$33 -> 0.15405988 | ... M34: =M33-$B$33 -> 0.24869233
A35: Valor aleación sin FAA | B35: =$B$27+B34 -> 24.12342 | C35: =$B$27+C34 -> 24.1382 | D35: =$B$27+D34 -> 24.159806 | E35: =$B$27+E34 -> 24.182989 | F35: =$B$27+F34 -> 24.206538 | G35: =$B$27+G34 -> 24.230171 | H35: =$B$27+H34 -> 24.253823 | I35: =$B$27+I34 -> 24.27748 | ... M35: =$B$27+M34 -> 24.372112
A36: Valor aleación con FAA | B36: =B35*(1+$B$6) -> 27.983167 | C36: =C35*(1+$B$6) -> 28.000312 | D36: =D35*(1+$B$6) -> 28.025375 | E36: =E35*(1+$B$6) -> 28.052268 | F36: =F35*(1+$B$6) -> 28.079584 | G36: =G35*(1+$B$6) -> 28.106998 | H36: =H35*(1+$B$6) -> 28.134435 | I36: =I35*(1+$B$6) -> 28.161877 | ... M36: =M35*(1+$B$6) -> 28.27165
A37: Costo transformación | B37: =$B$26 -> 17.945803 | C37: =$B$26 -> 17.945803 | D37: =$B$26 -> 17.945803 | E37: =$B$26 -> 17.945803 | F37: =$B$26 -> 17.945803 | G37: =$B$26 -> 17.945803 | H37: =$B$26 -> 17.945803 | I37: =$B$26 -> 17.945803 | ... M37: =$B$26 -> 17.945803
A40: PARÁMETROS POR DENOMINACIÓN | B40: $0.50 | C40: $1 | D40: $2 | E40: $5 | F40: $10 | G40: $20
A41: Gramos finales por pieza | B41: 0 | C41: 1.81 | D41: 2.38 | E41: 3.25 | F41: 5.579 | G41: 7.16
A42: Scrap | B42: 0 | C42: 0.269 | D42: 0.28 | E42: 0.28 | F42: 0.58 | G42: 0.59
A43: Rendimiento | B43: 1 | C43: 0.731 | D43: 0.72 | E43: 0.72 | F43: 0.42 | G43: 0.41
A46: TARIFAS CALCULADAS — BRONCE-ALUMINIO (MXN/pieza)
A47: Mes | B47: $0.50 | C47: $1 | D47: $2 | E47: $5 | F47: $10 | G47: $20
A48: Enero | B48: =ROUND((($B$26*$B$5)+((INDEX($B$36:$M$36,1,ROW()-47)*$B$5)-($B$7*(INDEX($B$35:$M$35,1,ROW()-47)*$B$5)*B$42)))/B$43*B$41/1000,6) -> 0 | C48: =ROUND((($B$26*$B$5)+((INDEX($B$36:$M$36,1,ROW()-47)*$B$5)-($B$7*(INDEX($B$35:$M$35,1,ROW()-47)*$B$5)*C$42)))/C$43*C$41/1000,6) -> 1.91238 | D48: =ROUND((($B$26*$B$5)+((INDEX($B$36:$M$36,1,ROW()-47)*$B$5)-($B$7*(INDEX($B$35:$M$35,1,ROW()-47)*$B$5)*D$42)))/D$43*D$41/1000,6) -> 2.537247 | E48: =ROUND((($B$26*$B$5)+((INDEX($B$36:$M$36,1,ROW()-47)*$B$5)-($B$7*(INDEX($B$35:$M$35,1,ROW()-47)*$B$5)*E$42)))/E$43*E$41/1000,6) -> 3.464728 | F48: =ROUND((($B$26*$B$5)+((INDEX($B$36:$M$36,1,ROW()-47)*$B$5)-($B$7*(INDEX($B$35:$M$35,1,ROW()-47)*$B$5)*F$42)))/F$43*F$41/1000,6) -> 8.465059 | G48: =ROUND((($B$26*$B$5)+((INDEX($B$36:$M$36,1,ROW()-47)*$B$5)-($B$7*(INDEX($B$35:$M$35,1,ROW()-47)*$B$5)*G$42)))/G$43*G$41/1000,6) -> 11.053046
A49: Febrero | B49: =ROUND((($B$26*$B$5)+((INDEX($B$36:$M$36,1,ROW()-47)*$B$5)-($B$7*(INDEX($B$35:$M$35,1,ROW()-47)*$B$5)*B$42)))/B$43*B$41/1000,6) -> 0 | C49: =ROUND((($B$26*$B$5)+((INDEX($B$36:$M$36,1,ROW()-47)*$B$5)-($B$7*(INDEX($B$35:$M$35,1,ROW()-47)*$B$5)*C$42)))/C$43*C$41/1000,6) -> 1.913025 | D49: =ROUND((($B$26*$B$5)+((INDEX($B$36:$M$36,1,ROW()-47)*$B$5)-($B$7*(INDEX($B$35:$M$35,1,ROW()-47)*$B$5)*D$42)))/D$43*D$41/1000,6) -> 2.538098 | E49: =ROUND((($B$26*$B$5)+((INDEX($B$36:$M$36,1,ROW()-47)*$B$5)-($B$7*(INDEX($B$35:$M$35,1,ROW()-47)*$B$5)*E$42)))/E$43*E$41/1000,6) -> 3.465889 | F49: =ROUND((($B$26*$B$5)+((INDEX($B$36:$M$36,1,ROW()-47)*$B$5)-($B$7*(INDEX($B$35:$M$35,1,ROW()-47)*$B$5)*F$42)))/F$43*F$41/1000,6) -> 8.467418 | G49: =ROUND((($B$26*$B$5)+((INDEX($B$36:$M$36,1,ROW()-47)*$B$5)-($B$7*(INDEX($B$35:$M$35,1,ROW()-47)*$B$5)*G$42)))/G$43*G$41/1000,6) -> 11.056101
A50: Marzo | B50: =ROUND((($B$26*$B$5)+((INDEX($B$36:$M$36,1,ROW()-47)*$B$5)-($B$7*(INDEX($B$35:$M$35,1,ROW()-47)*$B$5)*B$42)))/B$43*B$41/1000,6) -> 0 | C50: =ROUND((($B$26*$B$5)+((INDEX($B$36:$M$36,1,ROW()-47)*$B$5)-($B$7*(INDEX($B$35:$M$35,1,ROW()-47)*$B$5)*C$42)))/C$43*C$41/1000,6) -> 1.913967 | D50: =ROUND((($B$26*$B$5)+((INDEX($B$36:$M$36,1,ROW()-47)*$B$5)-($B$7*(INDEX($B$35:$M$35,1,ROW()-47)*$B$5)*D$42)))/D$43*D$41/1000,6) -> 2.539341 | E50: =ROUND((($B$26*$B$5)+((INDEX($B$36:$M$36,1,ROW()-47)*$B$5)-($B$7*(INDEX($B$35:$M$35,1,ROW()-47)*$B$5)*E$42)))/E$43*E$41/1000,6) -> 3.467588 | F50: =ROUND((($B$26*$B$5)+((INDEX($B$36:$M$36,1,ROW()-47)*$B$5)-($B$7*(INDEX($B$35:$M$35,1,ROW()-47)*$B$5)*F$42)))/F$43*F$41/1000,6) -> 8.470866 | G50: =ROUND((($B$26*$B$5)+((INDEX($B$36:$M$36,1,ROW()-47)*$B$5)-($B$7*(INDEX($B$35:$M$35,1,ROW()-47)*$B$5)*G$42)))/G$43*G$41/1000,6) -> 11.060566
A51: Abril | B51: =ROUND((($B$26*$B$5)+((INDEX($B$36:$M$36,1,ROW()-47)*$B$5)-($B$7*(INDEX($B$35:$M$35,1,ROW()-47)*$B$5)*B$42)))/B$43*B$41/1000,6) -> 0 | C51: =ROUND((($B$26*$B$5)+((INDEX($B$36:$M$36,1,ROW()-47)*$B$5)-($B$7*(INDEX($B$35:$M$35,1,ROW()-47)*$B$5)*C$42)))/C$43*C$41/1000,6) -> 1.914978 | D51: =ROUND((($B$26*$B$5)+((INDEX($B$36:$M$36,1,ROW()-47)*$B$5)-($B$7*(INDEX($B$35:$M$35,1,ROW()-47)*$B$5)*D$42)))/D$43*D$41/1000,6) -> 2.540676 | E51: =ROUND((($B$26*$B$5)+((INDEX($B$36:$M$36,1,ROW()-47)*$B$5)-($B$7*(INDEX($B$35:$M$35,1,ROW()-47)*$B$5)*E$42)))/E$43*E$41/1000,6) -> 3.469411 | F51: =ROUND((($B$26*$B$5)+((INDEX($B$36:$M$36,1,ROW()-47)*$B$5)-($B$7*(INDEX($B$35:$M$35,1,ROW()-47)*$B$5)*F$42)))/F$43*F$41/1000,6) -> 8.474566 | G51: =ROUND((($B$26*$B$5)+((INDEX($B$36:$M$36,1,ROW()-47)*$B$5)-($B$7*(INDEX($B$35:$M$35,1,ROW()-47)*$B$5)*G$42)))/G$43*G$41/1000,6) -> 11.065358
A52: Mayo | B52: =ROUND((($B$26*$B$5)+((INDEX($B$36:$M$36,1,ROW()-47)*$B$5)-($B$7*(INDEX($B$35:$M$35,1,ROW()-47)*$B$5)*B$42)))/B$43*B$41/1000,6) -> 0 | C52: =ROUND((($B$26*$B$5)+((INDEX($B$36:$M$36,1,ROW()-47)*$B$5)-($B$7*(INDEX($B$35:$M$35,1,ROW()-47)*$B$5)*C$42)))/C$43*C$41/1000,6) -> 1.916006 | D52: =ROUND((($B$26*$B$5)+((INDEX($B$36:$M$36,1,ROW()-47)*$B$5)-($B$7*(INDEX($B$35:$M$35,1,ROW()-47)*$B$5)*D$42)))/D$43*D$41/1000,6) -> 2.542032 | E52: =ROUND((($B$26*$B$5)+((INDEX($B$36:$M$36,1,ROW()-47)*$B$5)-($B$7*(INDEX($B$35:$M$35,1,ROW()-47)*$B$5)*E$42)))/E$43*E$41/1000,6) -> 3.471262 | F52: =ROUND((($B$26*$B$5)+((INDEX($B$36:$M$36,1,ROW()-47)*$B$5)-($B$7*(INDEX($B$35:$M$35,1,ROW()-47)*$B$5)*F$42)))/F$43*F$41/1000,6) -> 8.478325 | G52: =ROUND((($B$26*$B$5)+((INDEX($B$36:$M$36,1,ROW()-47)*$B$5)-($B$7*(INDEX($B$35:$M$35,1,ROW()-47)*$B$5)*G$42)))/G$43*G$41/1000,6) -> 11.070225
A53: Junio | B53: =ROUND((($B$26*$B$5)+((INDEX($B$36:$M$36,1,ROW()-47)*$B$5)-($B$7*(INDEX($B$35:$M$35,1,ROW()-47)*$B$5)*B$42)))/B$43*B$41/1000,6) -> 0 | C53: =ROUND((($B$26*$B$5)+((INDEX($B$36:$M$36,1,ROW()-47)*$B$5)-($B$7*(INDEX($B$35:$M$35,1,ROW()-47)*$B$5)*C$42)))/C$43*C$41/1000,6) -> 1.917036 | D53: =ROUND((($B$26*$B$5)+((INDEX($B$36:$M$36,1,ROW()-47)*$B$5)-($B$7*(INDEX($B$35:$M$35,1,ROW()-47)*$B$5)*D$42)))/D$43*D$41/1000,6) -> 2.543392 | E53: =ROUND((($B$26*$B$5)+((INDEX($B$36:$M$36,1,ROW()-47)*$B$5)-($B$7*(INDEX($B$35:$M$35,1,ROW()-47)*$B$5)*E$42)))/E$43*E$41/1000,6) -> 3.47312 | F53: =ROUND((($B$26*$B$5)+((INDEX($B$36:$M$36,1,ROW()-47)*$B$5)-($B$7*(INDEX($B$35:$M$35,1,ROW()-47)*$B$5)*F$42)))/F$43*F$41/1000,6) -> 8.482096 | G53: =ROUND((($B$26*$B$5)+((INDEX($B$36:$M$36,1,ROW()-47)*$B$5)-($B$7*(INDEX($B$35:$M$35,1,ROW()-47)*$B$5)*G$42)))/G$43*G$41/1000,6) -> 11.075109
A54: Julio | B54: =ROUND((($B$26*$B$5)+((INDEX($B$36:$M$36,1,ROW()-47)*$B$5)-($B$7*(INDEX($B$35:$M$35,1,ROW()-47)*$B$5)*B$42)))/B$43*B$41/1000,6) -> 0 | C54: =ROUND((($B$26*$B$5)+((INDEX($B$36:$M$36,1,ROW()-47)*$B$5)-($B$7*(INDEX($B$35:$M$35,1,ROW()-47)*$B$5)*C$42)))/C$43*C$41/1000,6) -> 1.918068 | D54: =ROUND((($B$26*$B$5)+((INDEX($B$36:$M$36,1,ROW()-47)*$B$5)-($B$7*(INDEX($B$35:$M$35,1,ROW()-47)*$B$5)*D$42)))/D$43*D$41/1000,6) -> 2.544754 | E54: =ROUND((($B$26*$B$5)+((INDEX($B$36:$M$36,1,ROW()-47)*$B$5)-($B$7*(INDEX($B$35:$M$35,1,ROW()-47)*$B$5)*E$42)))/E$43*E$41/1000,6) -> 3.474979 | F54: =ROUND((($B$26*$B$5)+((INDEX($B$36:$M$36,1,ROW()-47)*$B$5)-($B$7*(INDEX($B$35:$M$35,1,ROW()-47)*$B$5)*F$42)))/F$43*F$41/1000,6) -> 8.485871 | G54: =ROUND((($B$26*$B$5)+((INDEX($B$36:$M$36,1,ROW()-47)*$B$5)-($B$7*(INDEX($B$35:$M$35,1,ROW()-47)*$B$5)*G$42)))/G$43*G$41/1000,6) -> 11.079997
A55: Agosto | B55: =ROUND((($B$26*$B$5)+((INDEX($B$36:$M$36,1,ROW()-47)*$B$5)-($B$7*(INDEX($B$35:$M$35,1,ROW()-47)*$B$5)*B$42)))/B$43*B$41/1000,6) -> 0 | C55: =ROUND((($B$26*$B$5)+((INDEX($B$36:$M$36,1,ROW()-47)*$B$5)-($B$7*(INDEX($B$35:$M$35,1,ROW()-47)*$B$5)*C$42)))/C$43*C$41/1000,6) -> 1.9191 | D55: =ROUND((($B$26*$B$5)+((INDEX($B$36:$M$36,1,ROW()-47)*$B$5)-($B$7*(INDEX($B$35:$M$35,1,ROW()-47)*$B$5)*D$42)))/D$43*D$41/1000,6) -> 2.546116 | E55: =ROUND((($B$26*$B$5)+((INDEX($B$36:$M$36,1,ROW()-47)*$B$5)-($B$7*(INDEX($B$35:$M$35,1,ROW()-47)*$B$5)*E$42)))/E$43*E$41/1000,6) -> 3.476839 | F55: =ROUND((($B$26*$B$5)+((INDEX($B$36:$M$36,1,ROW()-47)*$B$5)-($B$7*(INDEX($B$35:$M$35,1,ROW()-47)*$B$5)*F$42)))/F$43*F$41/1000,6) -> 8.489647 | G55: =ROUND((($B$26*$B$5)+((INDEX($B$36:$M$36,1,ROW()-47)*$B$5)-($B$7*(INDEX($B$35:$M$35,1,ROW()-47)*$B$5)*G$42)))/G$43*G$41/1000,6) -> 11.084887
A56: Septiembre | B56: =ROUND((($B$26*$B$5)+((INDEX($B$36:$M$36,1,ROW()-47)*$B$5)-($B$7*(INDEX($B$35:$M$35,1,ROW()-47)*$B$5)*B$42)))/B$43*B$41/1000,6) -> 0 | C56: =ROUND((($B$26*$B$5)+((INDEX($B$36:$M$36,1,ROW()-47)*$B$5)-($B$7*(INDEX($B$35:$M$35,1,ROW()-47)*$B$5)*C$42)))/C$43*C$41/1000,6) -> 1.920131 | D56: =ROUND((($B$26*$B$5)+((INDEX($B$36:$M$36,1,ROW()-47)*$B$5)-($B$7*(INDEX($B$35:$M$35,1,ROW()-47)*$B$5)*D$42)))/D$43*D$41/1000,6) -> 2.547478 | E56: =ROUND((($B$26*$B$5)+((INDEX($B$36:$M$36,1,ROW()-47)*$B$5)-($B$7*(INDEX($B$35:$M$35,1,ROW()-47)*$B$5)*E$42)))/E$43*E$41/1000,6) -> 3.478699 | F56: =ROUND((($B$26*$B$5)+((INDEX($B$36:$M$36,1,ROW()-47)*$B$5)-($B$7*(INDEX($B$35:$M$35,1,ROW()-47)*$B$5)*F$42)))/F$43*F$41/1000,6) -> 8.493422 | G56: =ROUND((($B$26*$B$5)+((INDEX($B$36:$M$36,1,ROW()-47)*$B$5)-($B$7*(INDEX($B$35:$M$35,1,ROW()-47)*$B$5)*G$42)))/G$43*G$41/1000,6) -> 11.089776
A57: Octubre | B57: =ROUND((($B$26*$B$5)+((INDEX($B$36:$M$36,1,ROW()-47)*$B$5)-($B$7*(INDEX($B$35:$M$35,1,ROW()-47)*$B$5)*B$42)))/B$43*B$41/1000,6) -> 0 | C57: =ROUND((($B$26*$B$5)+((INDEX($B$36:$M$36,1,ROW()-47)*$B$5)-($B$7*(INDEX($B$35:$M$35,1,ROW()-47)*$B$5)*C$42)))/C$43*C$41/1000,6) -> 1.921163 | D57: =ROUND((($B$26*$B$5)+((INDEX($B$36:$M$36,1,ROW()-47)*$B$5)-($B$7*(INDEX($B$35:$M$35,1,ROW()-47)*$B$5)*D$42)))/D$43*D$41/1000,6) -> 2.54884 | E57: =ROUND((($B$26*$B$5)+((INDEX($B$36:$M$36,1,ROW()-47)*$B$5)-($B$7*(INDEX($B$35:$M$35,1,ROW()-47)*$B$5)*E$42)))/E$43*E$41/1000,6) -> 3.480559 | F57: =ROUND((($B$26*$B$5)+((INDEX($B$36:$M$36,1,ROW()-47)*$B$5)-($B$7*(INDEX($B$35:$M$35,1,ROW()-47)*$B$5)*F$42)))/F$43*F$41/1000,6) -> 8.497198 | G57: =ROUND((($B$26*$B$5)+((INDEX($B$36:$M$36,1,ROW()-47)*$B$5)-($B$7*(INDEX($B$35:$M$35,1,ROW()-47)*$B$5)*G$42)))/G$43*G$41/1000,6) -> 11.094666
A58: Noviembre | B58: =ROUND((($B$26*$B$5)+((INDEX($B$36:$M$36,1,ROW()-47)*$B$5)-($B$7*(INDEX($B$35:$M$35,1,ROW()-47)*$B$5)*B$42)))/B$43*B$41/1000,6) -> 0 | C58: =ROUND((($B$26*$B$5)+((INDEX($B$36:$M$36,1,ROW()-47)*$B$5)-($B$7*(INDEX($B$35:$M$35,1,ROW()-47)*$B$5)*C$42)))/C$43*C$41/1000,6) -> 1.922195 | D58: =ROUND((($B$26*$B$5)+((INDEX($B$36:$M$36,1,ROW()-47)*$B$5)-($B$7*(INDEX($B$35:$M$35,1,ROW()-47)*$B$5)*D$42)))/D$43*D$41/1000,6) -> 2.550202 | E58: =ROUND((($B$26*$B$5)+((INDEX($B$36:$M$36,1,ROW()-47)*$B$5)-($B$7*(INDEX($B$35:$M$35,1,ROW()-47)*$B$5)*E$42)))/E$43*E$41/1000,6) -> 3.482419 | F58: =ROUND((($B$26*$B$5)+((INDEX($B$36:$M$36,1,ROW()-47)*$B$5)-($B$7*(INDEX($B$35:$M$35,1,ROW()-47)*$B$5)*F$42)))/F$43*F$41/1000,6) -> 8.500974 | G58: =ROUND((($B$26*$B$5)+((INDEX($B$36:$M$36,1,ROW()-47)*$B$5)-($B$7*(INDEX($B$35:$M$35,1,ROW()-47)*$B$5)*G$42)))/G$43*G$41/1000,6) -> 11.099555
A59: Diciembre | B59: =ROUND((($B$26*$B$5)+((INDEX($B$36:$M$36,1,ROW()-47)*$B$5)-($B$7*(INDEX($B$35:$M$35,1,ROW()-47)*$B$5)*B$42)))/B$43*B$41/1000,6) -> 0 | C59: =ROUND((($B$26*$B$5)+((INDEX($B$36:$M$36,1,ROW()-47)*$B$5)-($B$7*(INDEX($B$35:$M$35,1,ROW()-47)*$B$5)*C$42)))/C$43*C$41/1000,6) -> 1.923227 | D59: =ROUND((($B$26*$B$5)+((INDEX($B$36:$M$36,1,ROW()-47)*$B$5)-($B$7*(INDEX($B$35:$M$35,1,ROW()-47)*$B$5)*D$42)))/D$43*D$41/1000,6) -> 2.551564 | E59: =ROUND((($B$26*$B$5)+((INDEX($B$36:$M$36,1,ROW()-47)*$B$5)-($B$7*(INDEX($B$35:$M$35,1,ROW()-47)*$B$5)*E$42)))/E$43*E$41/1000,6) -> 3.484278 | F59: =ROUND((($B$26*$B$5)+((INDEX($B$36:$M$36,1,ROW()-47)*$B$5)-($B$7*(INDEX($B$35:$M$35,1,ROW()-47)*$B$5)*F$42)))/F$43*F$41/1000,6) -> 8.50475 | G59: =ROUND((($B$26*$B$5)+((INDEX($B$36:$M$36,1,ROW()-47)*$B$5)-($B$7*(INDEX($B$35:$M$35,1,ROW()-47)*$B$5)*G$42)))/G$43*G$41/1000,6) -> 11.104445
A63: ALPACA / CUNI — FORMACIÓN DEL VALOR Y TARIFAS
A64: PARÁMETRO | B64: VALOR | C64: UNIDAD | D64: FUENTE / CRITERIO
A65: Composición cobre | B65: 0.65 | C65: % | D65: Fijo
A66: Composición níquel | B66: 0.1 | C66: % | D66: Fijo
A67: Composición zinc | B67: 0.25 | C67: % | D67: Fijo
A68: Premio cobre | B68: 0.188 | C68: USD/kg | D68: Fijo
A69: Premio níquel | B69: 1.05 | C69: USD/kg | D69: Fijo
A70: Premio zinc | B70: 0.359 | C70: USD/kg | D70: Fijo
A71: Costo transformación | B71: 2.9245154 | C71: USD/kg | D71: EJEMPLO ENERO 2
A73: CONCEPTO | B73: ENERO | C73: FEBRERO | D73: MARZO | E73: ABRIL | F73: MAYO | G73: JUNIO | H73: JULIO | I73: AGOSTO | J73: SEPTIEMBRE | K73: OCTUBRE | L73: NOVIEMBRE | M73: DICIEMBRE
A74: Componente Cu | B74: =('METALES 2025 BUENO'!C$12+$B$68)*$B$65 -> 5.9091912 | C74: =('METALES 2025 BUENO'!D$12+$B$68)*$B$65 -> 5.9193406 | D74: =('METALES 2025 BUENO'!E$12+$B$68)*$B$65 -> 5.9343123 | E74: =('METALES 2025 BUENO'!F$12+$B$68)*$B$65 -> 5.9503989 | F74: =('METALES 2025 BUENO'!G$12+$B$68)*$B$65 -> 5.9667434 | G74: =('METALES 2025 BUENO'!H$12+$B$68)*$B$65 -> 5.9831474 | H74: =('METALES 2025 BUENO'!I$12+$B$68)*$B$65 -> 5.9995652 | I74: =('METALES 2025 BUENO'!J$12+$B$68)*$B$65 -> 6.0159862 | ... M74: =('METALES 2025 BUENO'!N$12+$B$68)*$B$65 -> 6.0816738
A75: Componente Ni | B75: =('METALES 2025 BUENO'!C$14+$B$69)*$B$66 -> 1.652052 | C75: =('METALES 2025 BUENO'!D$14+$B$69)*$B$66 -> 1.652052 | D75: =('METALES 2025 BUENO'!E$14+$B$69)*$B$66 -> 1.652052 | E75: =('METALES 2025 BUENO'!F$14+$B$69)*$B$66 -> 1.652052 | F75: =('METALES 2025 BUENO'!G$14+$B$69)*$B$66 -> 1.652052 | G75: =('METALES 2025 BUENO'!H$14+$B$69)*$B$66 -> 1.652052 | H75: =('METALES 2025 BUENO'!I$14+$B$69)*$B$66 -> 1.652052 | I75: =('METALES 2025 BUENO'!J$14+$B$69)*$B$66 -> 1.652052 | ... M75: =('METALES 2025 BUENO'!N$14+$B$69)*$B$66 -> 1.652052
A76: Componente Zn | B76: =('METALES 2025 BUENO'!C$15+$B$70)*$B$67 -> 0.85139099 | C76: =('METALES 2025 BUENO'!D$15+$B$70)*$B$67 -> 0.85174793 | D76: =('METALES 2025 BUENO'!E$15+$B$70)*$B$67 -> 0.85189105 | E76: =('METALES 2025 BUENO'!F$15+$B$70)*$B$67 -> 0.85194844 | F76: =('METALES 2025 BUENO'!G$15+$B$70)*$B$67 -> 0.85197145 | G76: =('METALES 2025 BUENO'!H$15+$B$70)*$B$67 -> 0.85198068 | H76: =('METALES 2025 BUENO'!I$15+$B$70)*$B$67 -> 0.85198438 | I76: =('METALES 2025 BUENO'!J$15+$B$70)*$B$67 -> 0.85198587 | ... M76: =('METALES 2025 BUENO'!N$15+$B$70)*$B$67 -> 0.85198683
A77: Valor aleación sin FAA | B77: =SUM(B74:B76) -> 8.4126342 | C77: =SUM(C74:C76) -> 8.4231405 | D77: =SUM(D74:D76) -> 8.4382553 | E77: =SUM(E74:E76) -> 8.4543994 | F77: =SUM(F74:F76) -> 8.4707668 | G77: =SUM(G74:G76) -> 8.4871801 | H77: =SUM(H74:H76) -> 8.5036016 | I77: =SUM(I74:I76) -> 8.5200241 | ... M77: =SUM(M74:M76) -> 8.5857126
A78: Valor aleación con FAA | B78: =B77*(1+$B$6) -> 9.7586556 | C78: =C77*(1+$B$6) -> 9.770843 | D78: =D77*(1+$B$6) -> 9.7883762 | E78: =E77*(1+$B$6) -> 9.8071033 | F78: =F77*(1+$B$6) -> 9.8260895 | G78: =G77*(1+$B$6) -> 9.8451289 | H78: =H77*(1+$B$6) -> 9.8641778 | I78: =I77*(1+$B$6) -> 9.8832279 | ... M78: =M77*(1+$B$6) -> 9.9594266
A79: Costo transformación | B79: =$B$71 -> 2.9245154 | C79: =$B$71 -> 2.9245154 | D79: =$B$71 -> 2.9245154 | E79: =$B$71 -> 2.9245154 | F79: =$B$71 -> 2.9245154 | G79: =$B$71 -> 2.9245154 | H79: =$B$71 -> 2.9245154 | I79: =$B$71 -> 2.9245154 | ... M79: =$B$71 -> 2.9245154
A82: PARÁMETROS POR DENOMINACIÓN | B82: $0.50 | C82: $1 | D82: $2 | E82: $5 | F82: $10 | G82: $20
A83: Gramos finales por pieza | B83: 0 | C83: 0 | D83: 0 | E83: 0 | F83: 4.75 | G83: 5.51
A84: Scrap | B84: 0 | C84: 0 | D84: 0 | E84: 0 | F84: 0.29 | G84: 0.29
A85: Rendimiento | B85: 1 | C85: 1 | D85: 1 | E85: 1 | F85: 0.71 | G85: 0.71
A88: TARIFAS CALCULADAS — ALPACA / CUNI (MXN/pieza)
A89: Mes | B89: $0.50 | C89: $1 | D89: $2 | E89: $5 | F89: $10 | G89: $20
A90: Enero | B90: =ROUND((($B$71*$B$5)+((INDEX($B$78:$M$78,1,ROW()-88)*$B$5)-($B$7*(INDEX($B$77:$M$77,1,ROW()-88)*$B$5)*B$84)))/B$85*B$83/1000,6) -> 0 | C90: =ROUND((($B$71*$B$5)+((INDEX($B$78:$M$78,1,ROW()-88)*$B$5)-($B$7*(INDEX($B$77:$M$77,1,ROW()-88)*$B$5)*C$84)))/C$85*C$83/1000,6) -> 0 | D90: =ROUND((($B$71*$B$5)+((INDEX($B$78:$M$78,1,ROW()-88)*$B$5)-($B$7*(INDEX($B$77:$M$77,1,ROW()-88)*$B$5)*D$84)))/D$85*D$83/1000,6) -> 0 | E90: =ROUND((($B$71*$B$5)+((INDEX($B$78:$M$78,1,ROW()-88)*$B$5)-($B$7*(INDEX($B$77:$M$77,1,ROW()-88)*$B$5)*E$84)))/E$85*E$83/1000,6) -> 0 | F90: {=ROUND((($B$71*$B$5)+((INDEX($B$78:$M$78,1,ROWS($A$90:A90))*$B$5)-($B$7*(INDEX($B$77:$M$77,1,ROWS($A$90:A90))*$B$5)*F$84)))/F$85*F$83/1000,6)} -> 1.34887 | G90: {=ROUND((($B$71*$B$5)+((INDEX($B$78:$M$78,1,ROWS($A$90:A90))*$B$5)-($B$7*(INDEX($B$77:$M$77,1,ROWS($A$90:A90))*$B$5)*G$84)))/G$85*G$83/1000,6)} -> 1.564689
A91: Febrero | B91: =ROUND((($B$71*$B$5)+((INDEX($B$78:$M$78,1,ROW()-88)*$B$5)-($B$7*(INDEX($B$77:$M$77,1,ROW()-88)*$B$5)*B$84)))/B$85*B$83/1000,6) -> 0 | C91: =ROUND((($B$71*$B$5)+((INDEX($B$78:$M$78,1,ROW()-88)*$B$5)-($B$7*(INDEX($B$77:$M$77,1,ROW()-88)*$B$5)*C$84)))/C$85*C$83/1000,6) -> 0 | D91: =ROUND((($B$71*$B$5)+((INDEX($B$78:$M$78,1,ROW()-88)*$B$5)-($B$7*(INDEX($B$77:$M$77,1,ROW()-88)*$B$5)*D$84)))/D$85*D$83/1000,6) -> 0 | E91: =ROUND((($B$71*$B$5)+((INDEX($B$78:$M$78,1,ROW()-88)*$B$5)-($B$7*(INDEX($B$77:$M$77,1,ROW()-88)*$B$5)*E$84)))/E$85*E$83/1000,6) -> 0 | F91: {=ROUND((($B$71*$B$5)+((INDEX($B$78:$M$78,1,ROWS($A$90:A91))*$B$5)-($B$7*(INDEX($B$77:$M$77,1,ROWS($A$90:A91))*$B$5)*F$84)))/F$85*F$83/1000,6)} -> 1.350081 | G91: {=ROUND((($B$71*$B$5)+((INDEX($B$78:$M$78,1,ROWS($A$90:A91))*$B$5)-($B$7*(INDEX($B$77:$M$77,1,ROWS($A$90:A91))*$B$5)*G$84)))/G$85*G$83/1000,6)} -> 1.566094
A92: Marzo | B92: =ROUND((($B$71*$B$5)+((INDEX($B$78:$M$78,1,ROW()-88)*$B$5)-($B$7*(INDEX($B$77:$M$77,1,ROW()-88)*$B$5)*B$84)))/B$85*B$83/1000,6) -> 0 | C92: =ROUND((($B$71*$B$5)+((INDEX($B$78:$M$78,1,ROW()-88)*$B$5)-($B$7*(INDEX($B$77:$M$77,1,ROW()-88)*$B$5)*C$84)))/C$85*C$83/1000,6) -> 0 | D92: =ROUND((($B$71*$B$5)+((INDEX($B$78:$M$78,1,ROW()-88)*$B$5)-($B$7*(INDEX($B$77:$M$77,1,ROW()-88)*$B$5)*D$84)))/D$85*D$83/1000,6) -> 0 | E92: =ROUND((($B$71*$B$5)+((INDEX($B$78:$M$78,1,ROW()-88)*$B$5)-($B$7*(INDEX($B$77:$M$77,1,ROW()-88)*$B$5)*E$84)))/E$85*E$83/1000,6) -> 0 | F92: {=ROUND((($B$71*$B$5)+((INDEX($B$78:$M$78,1,ROWS($A$90:A92))*$B$5)-($B$7*(INDEX($B$77:$M$77,1,ROWS($A$90:A92))*$B$5)*F$84)))/F$85*F$83/1000,6)} -> 1.351824 | G92: {=ROUND((($B$71*$B$5)+((INDEX($B$78:$M$78,1,ROWS($A$90:A92))*$B$5)-($B$7*(INDEX($B$77:$M$77,1,ROWS($A$90:A92))*$B$5)*G$84)))/G$85*G$83/1000,6)} -> 1.568116
A93: Abril | B93: =ROUND((($B$71*$B$5)+((INDEX($B$78:$M$78,1,ROW()-88)*$B$5)-($B$7*(INDEX($B$77:$M$77,1,ROW()-88)*$B$5)*B$84)))/B$85*B$83/1000,6) -> 0 | C93: =ROUND((($B$71*$B$5)+((INDEX($B$78:$M$78,1,ROW()-88)*$B$5)-($B$7*(INDEX($B$77:$M$77,1,ROW()-88)*$B$5)*C$84)))/C$85*C$83/1000,6) -> 0 | D93: =ROUND((($B$71*$B$5)+((INDEX($B$78:$M$78,1,ROW()-88)*$B$5)-($B$7*(INDEX($B$77:$M$77,1,ROW()-88)*$B$5)*D$84)))/D$85*D$83/1000,6) -> 0 | E93: =ROUND((($B$71*$B$5)+((INDEX($B$78:$M$78,1,ROW()-88)*$B$5)-($B$7*(INDEX($B$77:$M$77,1,ROW()-88)*$B$5)*E$84)))/E$85*E$83/1000,6) -> 0 | F93: {=ROUND((($B$71*$B$5)+((INDEX($B$78:$M$78,1,ROWS($A$90:A93))*$B$5)-($B$7*(INDEX($B$77:$M$77,1,ROWS($A$90:A93))*$B$5)*F$84)))/F$85*F$83/1000,6)} -> 1.353686 | G93: {=ROUND((($B$71*$B$5)+((INDEX($B$78:$M$78,1,ROWS($A$90:A93))*$B$5)-($B$7*(INDEX($B$77:$M$77,1,ROWS($A$90:A93))*$B$5)*G$84)))/G$85*G$83/1000,6)} -> 1.570276
A94: Mayo | B94: =ROUND((($B$71*$B$5)+((INDEX($B$78:$M$78,1,ROW()-88)*$B$5)-($B$7*(INDEX($B$77:$M$77,1,ROW()-88)*$B$5)*B$84)))/B$85*B$83/1000,6) -> 0 | C94: =ROUND((($B$71*$B$5)+((INDEX($B$78:$M$78,1,ROW()-88)*$B$5)-($B$7*(INDEX($B$77:$M$77,1,ROW()-88)*$B$5)*C$84)))/C$85*C$83/1000,6) -> 0 | D94: =ROUND((($B$71*$B$5)+((INDEX($B$78:$M$78,1,ROW()-88)*$B$5)-($B$7*(INDEX($B$77:$M$77,1,ROW()-88)*$B$5)*D$84)))/D$85*D$83/1000,6) -> 0 | E94: =ROUND((($B$71*$B$5)+((INDEX($B$78:$M$78,1,ROW()-88)*$B$5)-($B$7*(INDEX($B$77:$M$77,1,ROW()-88)*$B$5)*E$84)))/E$85*E$83/1000,6) -> 0 | F94: {=ROUND((($B$71*$B$5)+((INDEX($B$78:$M$78,1,ROWS($A$90:A94))*$B$5)-($B$7*(INDEX($B$77:$M$77,1,ROWS($A$90:A94))*$B$5)*F$84)))/F$85*F$83/1000,6)} -> 1.355573 | G94: {=ROUND((($B$71*$B$5)+((INDEX($B$78:$M$78,1,ROWS($A$90:A94))*$B$5)-($B$7*(INDEX($B$77:$M$77,1,ROWS($A$90:A94))*$B$5)*G$84)))/G$85*G$83/1000,6)} -> 1.572465
A95: Junio | B95: =ROUND((($B$71*$B$5)+((INDEX($B$78:$M$78,1,ROW()-88)*$B$5)-($B$7*(INDEX($B$77:$M$77,1,ROW()-88)*$B$5)*B$84)))/B$85*B$83/1000,6) -> 0 | C95: =ROUND((($B$71*$B$5)+((INDEX($B$78:$M$78,1,ROW()-88)*$B$5)-($B$7*(INDEX($B$77:$M$77,1,ROW()-88)*$B$5)*C$84)))/C$85*C$83/1000,6) -> 0 | D95: =ROUND((($B$71*$B$5)+((INDEX($B$78:$M$78,1,ROW()-88)*$B$5)-($B$7*(INDEX($B$77:$M$77,1,ROW()-88)*$B$5)*D$84)))/D$85*D$83/1000,6) -> 0 | E95: =ROUND((($B$71*$B$5)+((INDEX($B$78:$M$78,1,ROW()-88)*$B$5)-($B$7*(INDEX($B$77:$M$77,1,ROW()-88)*$B$5)*E$84)))/E$85*E$83/1000,6) -> 0 | F95: {=ROUND((($B$71*$B$5)+((INDEX($B$78:$M$78,1,ROWS($A$90:A95))*$B$5)-($B$7*(INDEX($B$77:$M$77,1,ROWS($A$90:A95))*$B$5)*F$84)))/F$85*F$83/1000,6)} -> 1.357466 | G95: {=ROUND((($B$71*$B$5)+((INDEX($B$78:$M$78,1,ROWS($A$90:A95))*$B$5)-($B$7*(INDEX($B$77:$M$77,1,ROWS($A$90:A95))*$B$5)*G$84)))/G$85*G$83/1000,6)} -> 1.57466
A96: Julio | B96: =ROUND((($B$71*$B$5)+((INDEX($B$78:$M$78,1,ROW()-88)*$B$5)-($B$7*(INDEX($B$77:$M$77,1,ROW()-88)*$B$5)*B$84)))/B$85*B$83/1000,6) -> 0 | C96: =ROUND((($B$71*$B$5)+((INDEX($B$78:$M$78,1,ROW()-88)*$B$5)-($B$7*(INDEX($B$77:$M$77,1,ROW()-88)*$B$5)*C$84)))/C$85*C$83/1000,6) -> 0 | D96: =ROUND((($B$71*$B$5)+((INDEX($B$78:$M$78,1,ROW()-88)*$B$5)-($B$7*(INDEX($B$77:$M$77,1,ROW()-88)*$B$5)*D$84)))/D$85*D$83/1000,6) -> 0 | E96: =ROUND((($B$71*$B$5)+((INDEX($B$78:$M$78,1,ROW()-88)*$B$5)-($B$7*(INDEX($B$77:$M$77,1,ROW()-88)*$B$5)*E$84)))/E$85*E$83/1000,6) -> 0 | F96: {=ROUND((($B$71*$B$5)+((INDEX($B$78:$M$78,1,ROWS($A$90:A96))*$B$5)-($B$7*(INDEX($B$77:$M$77,1,ROWS($A$90:A96))*$B$5)*F$84)))/F$85*F$83/1000,6)} -> 1.359359 | G96: {=ROUND((($B$71*$B$5)+((INDEX($B$78:$M$78,1,ROWS($A$90:A96))*$B$5)-($B$7*(INDEX($B$77:$M$77,1,ROWS($A$90:A96))*$B$5)*G$84)))/G$85*G$83/1000,6)} -> 1.576857
A97: Agosto | B97: =ROUND((($B$71*$B$5)+((INDEX($B$78:$M$78,1,ROW()-88)*$B$5)-($B$7*(INDEX($B$77:$M$77,1,ROW()-88)*$B$5)*B$84)))/B$85*B$83/1000,6) -> 0 | C97: =ROUND((($B$71*$B$5)+((INDEX($B$78:$M$78,1,ROW()-88)*$B$5)-($B$7*(INDEX($B$77:$M$77,1,ROW()-88)*$B$5)*C$84)))/C$85*C$83/1000,6) -> 0 | D97: =ROUND((($B$71*$B$5)+((INDEX($B$78:$M$78,1,ROW()-88)*$B$5)-($B$7*(INDEX($B$77:$M$77,1,ROW()-88)*$B$5)*D$84)))/D$85*D$83/1000,6) -> 0 | E97: =ROUND((($B$71*$B$5)+((INDEX($B$78:$M$78,1,ROW()-88)*$B$5)-($B$7*(INDEX($B$77:$M$77,1,ROW()-88)*$B$5)*E$84)))/E$85*E$83/1000,6) -> 0 | F97: {=ROUND((($B$71*$B$5)+((INDEX($B$78:$M$78,1,ROWS($A$90:A97))*$B$5)-($B$7*(INDEX($B$77:$M$77,1,ROWS($A$90:A97))*$B$5)*F$84)))/F$85*F$83/1000,6)} -> 1.361253 | G97: {=ROUND((($B$71*$B$5)+((INDEX($B$78:$M$78,1,ROWS($A$90:A97))*$B$5)-($B$7*(INDEX($B$77:$M$77,1,ROWS($A$90:A97))*$B$5)*G$84)))/G$85*G$83/1000,6)} -> 1.579054
A98: Septiembre | B98: =ROUND((($B$71*$B$5)+((INDEX($B$78:$M$78,1,ROW()-88)*$B$5)-($B$7*(INDEX($B$77:$M$77,1,ROW()-88)*$B$5)*B$84)))/B$85*B$83/1000,6) -> 0 | C98: =ROUND((($B$71*$B$5)+((INDEX($B$78:$M$78,1,ROW()-88)*$B$5)-($B$7*(INDEX($B$77:$M$77,1,ROW()-88)*$B$5)*C$84)))/C$85*C$83/1000,6) -> 0 | D98: =ROUND((($B$71*$B$5)+((INDEX($B$78:$M$78,1,ROW()-88)*$B$5)-($B$7*(INDEX($B$77:$M$77,1,ROW()-88)*$B$5)*D$84)))/D$85*D$83/1000,6) -> 0 | E98: =ROUND((($B$71*$B$5)+((INDEX($B$78:$M$78,1,ROW()-88)*$B$5)-($B$7*(INDEX($B$77:$M$77,1,ROW()-88)*$B$5)*E$84)))/E$85*E$83/1000,6) -> 0 | F98: {=ROUND((($B$71*$B$5)+((INDEX($B$78:$M$78,1,ROWS($A$90:A98))*$B$5)-($B$7*(INDEX($B$77:$M$77,1,ROWS($A$90:A98))*$B$5)*F$84)))/F$85*F$83/1000,6)} -> 1.363147 | G98: {=ROUND((($B$71*$B$5)+((INDEX($B$78:$M$78,1,ROWS($A$90:A98))*$B$5)-($B$7*(INDEX($B$77:$M$77,1,ROWS($A$90:A98))*$B$5)*G$84)))/G$85*G$83/1000,6)} -> 1.58125
A99: Octubre | B99: =ROUND((($B$71*$B$5)+((INDEX($B$78:$M$78,1,ROW()-88)*$B$5)-($B$7*(INDEX($B$77:$M$77,1,ROW()-88)*$B$5)*B$84)))/B$85*B$83/1000,6) -> 0 | C99: =ROUND((($B$71*$B$5)+((INDEX($B$78:$M$78,1,ROW()-88)*$B$5)-($B$7*(INDEX($B$77:$M$77,1,ROW()-88)*$B$5)*C$84)))/C$85*C$83/1000,6) -> 0 | D99: =ROUND((($B$71*$B$5)+((INDEX($B$78:$M$78,1,ROW()-88)*$B$5)-($B$7*(INDEX($B$77:$M$77,1,ROW()-88)*$B$5)*D$84)))/D$85*D$83/1000,6) -> 0 | E99: =ROUND((($B$71*$B$5)+((INDEX($B$78:$M$78,1,ROW()-88)*$B$5)-($B$7*(INDEX($B$77:$M$77,1,ROW()-88)*$B$5)*E$84)))/E$85*E$83/1000,6) -> 0 | F99: {=ROUND((($B$71*$B$5)+((INDEX($B$78:$M$78,1,ROWS($A$90:A99))*$B$5)-($B$7*(INDEX($B$77:$M$77,1,ROWS($A$90:A99))*$B$5)*F$84)))/F$85*F$83/1000,6)} -> 1.365041 | G99: {=ROUND((($B$71*$B$5)+((INDEX($B$78:$M$78,1,ROWS($A$90:A99))*$B$5)-($B$7*(INDEX($B$77:$M$77,1,ROWS($A$90:A99))*$B$5)*G$84)))/G$85*G$83/1000,6)} -> 1.583447
A100: Noviembre | B100: =ROUND((($B$71*$B$5)+((INDEX($B$78:$M$78,1,ROW()-88)*$B$5)-($B$7*(INDEX($B$77:$M$77,1,ROW()-88)*$B$5)*B$84)))/B$85*B$83/1000,6) -> 0 | C100: =ROUND((($B$71*$B$5)+((INDEX($B$78:$M$78,1,ROW()-88)*$B$5)-($B$7*(INDEX($B$77:$M$77,1,ROW()-88)*$B$5)*C$84)))/C$85*C$83/1000,6) -> 0 | D100: =ROUND((($B$71*$B$5)+((INDEX($B$78:$M$78,1,ROW()-88)*$B$5)-($B$7*(INDEX($B$77:$M$77,1,ROW()-88)*$B$5)*D$84)))/D$85*D$83/1000,6) -> 0 | E100: =ROUND((($B$71*$B$5)+((INDEX($B$78:$M$78,1,ROW()-88)*$B$5)-($B$7*(INDEX($B$77:$M$77,1,ROW()-88)*$B$5)*E$84)))/E$85*E$83/1000,6) -> 0 | F100: {=ROUND((($B$71*$B$5)+((INDEX($B$78:$M$78,1,ROWS($A$90:A100))*$B$5)-($B$7*(INDEX($B$77:$M$77,1,ROWS($A$90:A100))*$B$5)*F$84)))/F$85*F$83/1000,6)} -> 1.366934 | G100: {=ROUND((($B$71*$B$5)+((INDEX($B$78:$M$78,1,ROWS($A$90:A100))*$B$5)-($B$7*(INDEX($B$77:$M$77,1,ROWS($A$90:A100))*$B$5)*G$84)))/G$85*G$83/1000,6)} -> 1.585644
A101: Diciembre | B101: 0 | C101: 0 | D101: 0 | E101: 0 | F101: {=ROUND((($B$71*$B$5)+((INDEX($B$78:$M$78,1,ROWS($A$90:A101))*$B$5)-($B$7*(INDEX($B$77:$M$77,1,ROWS($A$90:A101))*$B$5)*F$84)))/F$85*F$83/1000,6)} -> 1.368828 | G101: {=ROUND((($B$71*$B$5)+((INDEX($B$78:$M$78,1,ROWS($A$90:A101))*$B$5)-($B$7*(INDEX($B$77:$M$77,1,ROWS($A$90:A101))*$B$5)*G$84)))/G$85*G$83/1000,6)} -> 1.58784
A106: ACERO INOXIDABLE — TARIFAS BASE
A107: CONCEPTO | B107: $0.50 | C107: $1 | D107: $2 | E107: $5 | F107: $10 | G107: $20
A108: Costo base USD/pieza | B108: 0.015446687 | C108: 0.018228633 | D108: 0.024340027 | E108: 0.033492997 | F108: 0 | G108: 0
A109: Tarifa MXN/pieza | B109: =B108*$B$5 -> 0.29904787 | C109: =C108*$B$5 -> 0.35290633 | D109: =D108*$B$5 -> 0.47122292 | E109: =E108*$B$5 -> 0.64842443 | F109: =F108*$B$5 -> 0 | G109: =G108*$B$5 -> 0
A111: REFERENCIA COMERCIAL ACERO | B111: VALOR | C111: UNIDAD | D111: NOTA
A112: Precio base acero | B112: 1780.93 | C112: USD/ton | D112: Referencia proporcionada
A113: Sobrecargo | B113: 1.311901 | C113: USD/kg | D113: Referencia proporcionada
A114: Uso | B114: Informativo | D114: No alimenta la tarifa por pieza mientras no exista fórmula contractual completa de conversión.
A116: TARIFAS CALCULADAS — ACERO INOXIDABLE (MXN/pieza)
A117: Mes | B117: $0.50 | C117: $1 | D117: $2 | E117: $5 | F117: $10 | G117: $20
A118: Enero | B118: =B$109 -> 0.29904787 | C118: =C$109 -> 0.35290633 | D118: =D$109 -> 0.47122292 | E118: =E$109 -> 0.64842443 | F118: =F$109 -> 0 | G118: =G$109 -> 0
A119: Febrero | B119: =B$109 -> 0.29904787 | C119: =C$109 -> 0.35290633 | D119: =D$109 -> 0.47122292 | E119: =E$109 -> 0.64842443 | F119: =F$109 -> 0 | G119: =G$109 -> 0
A120: Marzo | B120: =B$109 -> 0.29904787 | C120: =C$109 -> 0.35290633 | D120: =D$109 -> 0.47122292 | E120: =E$109 -> 0.64842443 | F120: =F$109 -> 0 | G120: =G$109 -> 0
A121: Abril | B121: =B$109 -> 0.29904787 | C121: =C$109 -> 0.35290633 | D121: =D$109 -> 0.47122292 | E121: =E$109 -> 0.64842443 | F121: =F$109 -> 0 | G121: =G$109 -> 0
A122: Mayo | B122: =B$109 -> 0.29904787 | C122: =C$109 -> 0.35290633 | D122: =D$109 -> 0.47122292 | E122: =E$109 -> 0.64842443 | F122: =F$109 -> 0 | G122: =G$109 -> 0
A123: Junio | B123: =B$109 -> 0.29904787 | C123: =C$109 -> 0.35290633 | D123: =D$109 -> 0.47122292 | E123: =E$109 -> 0.64842443 | F123: =F$109 -> 0 | G123: =G$109 -> 0
...
